Workbook

Sheet START
A1: Preparation tracker | B1: One workbook for the whole plan. Fill it in daily; it takes about 5 minutes.
A3: How dates work | B3: Change the START DATE below to the Monday you start. Every date in DAILY moves with it.
A4: START DATE (a Monday) | B4: 46321
A6: DAILY | B6: One row per day (224). Status: Not started / In progress / Done / Needs review / Deferred. 'Done' only when the day's 'Done when' is true.
A7: DSA_LOG | B7: Every planned problem, pre-filled. Fill Result, the date and the six fields. Re-solve dates calculate themselves (D+1, 3, 7, 14).
A8: REVIEW | B8: Every 'explain aloud' question, pre-filled. Enter the date you learned it; review dates calculate (D+1, 3, 7, 14, 30).
A9: WEAK | B9: Anything you could not explain or solve. Exit rule: two successful recalls at least 7 days apart.
A10: DESIGNS | B10: Every HLD and LLD with its planned day. Score yourself out of 20 with the practice rubric.
A11: STORIES | B11: Your real stories mapped to the 16 Amazon Leadership Principles. Never invent; leave unknown numbers blank.
A12: JOURNAL | B12: One line per working day: problem, decision, outcome. This becomes your story bank.
A13: PROJECT | B13: Milestones M1–M12 with acceptance tests.
A14: APPLY / INTERVIEWS | B14: Applications from Week 21; an analysis within 24 hours of every interview.
A15: DASHBOARD | B15: Counts that update themselves.

Sheet DAILY
A1: Day | B1: Date | C1: Weekday | D1: Week | E1: Phase | F1: Focus | G1: DSA problems | H1: Core / rotating topic | I1: Explain aloud | J1: Status | K1: Minutes | L1: Recall | M1: Week file | N1: Notes
A2: 1 | B2: =START!$B$4+A2-1 | C2: =TEXT(B2,"ddd") | D2: 1 | E2: Foundations | F2: Array representation and traversal | G2: Array basics: print, sum, max, min, count of a target (handle empty input) | H2: C# program basics: a console project, variables and built-in types, arrays and Length | I2: Why is reading a[i] O(1) but finding a value O(n)? | J2: Not started | M2: =HYPERLINK("WEEKS/WEEK_01.md","Week 1 · Day 1")
A3: 2 | B3: =START!$B$4+A3-1 | C3: =TEXT(B3,"ddd") | D3: 1 | E3: Foundations | F3: Indexes, linear search and operation costs | G3: Linear search, first/last occurrence, minimum/maximum with index | H3: int vs long, integer division, overflow, checked arithmetic and conversions | I3: What is overflow and when should a sum use long? | J3: Not started | M3: =HYPERLINK("WEEKS/WEEK_01.md","Week 1 · Day 2")
A4: 3 | B4: =START!$B$4+A4-1 | C4: =TEXT(B4,"ddd") | D4: 1 | E4: Foundations | F4: Swapping and reversing in place | G4: Reverse an array in place with two indexes (0, 1, odd, even lengths) | H4: Methods, parameters, return values; value types vs reference types | I4: What does a variable of a value type hold, and what does a reference-type variable hold? | J4: Not started | M4: =HYPERLINK("WEEKS/WEEK_01.md","Week 1 · Day 3")
A5: 4 | B5: =START!$B$4+A5-1 | C5: =TEXT(B5,"ddd") | D5: 1 | E5: Foundations | F5: Sorted check and second-largest distinct | G5: Check sorted order; second-largest DISTINCT value | H5: Stack vs heap, where structs actually live, null vs empty, alias vs copy | I5: Where does a struct live — the stack or the heap? (It depends on where it is declared.) | J5: Not started | M5: =HYPERLINK("WEEKS/WEEK_01.md","Week 1 · Day 4")
A6: 5 | B6: =START!$B$4+A6-1 | C6: =TEXT(B6,"ddd") | D6: 1 | E6: Foundations | F6: Repair and retrieval | G6: re-solves + Concatenation of Array | H6: re-explain the week | J6: Not started | M6: =HYPERLINK("WEEKS/WEEK_01.md","Week 1 · Day 5")
A7: 6 | B7: =START!$B$4+A7-1 | C7: =TEXT(B7,"ddd") | D7: 1 | E7: Foundations | F7: Deep work: DSA + design + lab/project | G7: Insert / delete at an index by shifting, with spare capacity, Contains Duplicate | H7: How a web request works, on paper: client → DNS → server → API → database → response. Draw it. No scaling yet. | J7: Not started | M7: =HYPERLINK("WEEKS/WEEK_01.md","Week 1 · Day 6")
A8: 7 | B8: =START!$B$4+A8-1 | C8: =TEXT(B8,"ddd") | D8: 1 | E8: Foundations | F8: Weekly test, review, project, stories | H8: Predict-then-run lab: write 6 small C# examples about assignment and parameters (int, struct, class, array, string, ref) | J8: Not started | M8: =HYPERLINK("WEEKS/WEEK_01.md","Week 1 · Day 7")
A9: 8 | B9: =START!$B$4+A9-1 | C9: =TEXT(B9,"ddd") | D9: 2 | E9: Foundations | F9: Set membership and duplicate detection | G9: Contains Duplicate, Frequency map of an int[] with Dictionary (TryGetValue) | H9: Struct vs class, boxing and its hidden cost, nullable value types | I9: What is boxing, what does it cost, and name three places it happens by accident. | J9: Not started | M9: =HYPERLINK("WEEKS/WEEK_02.md","Week 2 · Day 8")
A10: 9 | B10: =START!$B$4+A10-1 | C10: =TEXT(B10,"ddd") | D10: 2 | E10: Foundations | F10: Two Sum, brute force first | G10: Two Sum | H10: Equality: ==, Equals, GetHashCode, IEquatable<T>, records | I10: State the Equals/GetHashCode contract and what breaks without it. | J10: Not started | M10: =HYPERLINK("WEEKS/WEEK_02.md","Week 2 · Day 9")
A11: 10 | B11: =START!$B$4+A11-1 | C11: =TEXT(B11,"ddd") | D11: 2 | E11: Foundations | F11: Two Sum in one pass with a map | G11: Two Sum, Longest Consecutive Sequence | H11: List<T>, Dictionary and HashSet internals: growth, buckets, collisions | I11: Why is Dictionary lookup O(1) on average, and what makes it O(n)? | J11: Not started | M11: =HYPERLINK("WEEKS/WEEK_02.md","Week 2 · Day 10")
A12: 11 | B12: =START!$B$4+A12-1 | C12: =TEXT(B12,"ddd") | D12: 2 | E12: Foundations | F12: Reader and writer pointers | G12: Move Zeroes, Remove Element | H12: ref, out, in; const vs readonly vs static; static constructors; object memory layout | I12: Explain ref, out and in in one sentence each. | J12: Not started | M12: =HYPERLINK("WEEKS/WEEK_02.md","Week 2 · Day 11")
A13: 12 | B13: =START!$B$4+A13-1 | C13: =TEXT(B13,"ddd") | D13: 2 | E13: Foundations | F13: Repair and retrieval | G13: re-solves + Find All Numbers Disappeared in an Array | H13: re-explain the week | J13: Not started | M13: =HYPERLINK("WEEKS/WEEK_02.md","Week 2 · Day 12")
A14: 13 | B14: =START!$B$4+A14-1 | C14: =TEXT(B14,"ddd") | D14: 2 | E14: Foundations | F14: Deep work: DSA + design + lab/project | G14: Remove Duplicates from Sorted Array, Running Sum of 1d Array, Plus One, Merge Sorted Array, Range Sum Query - Immutable | H14: API contract on paper: POST /jobs and GET /jobs/{id} — inputs, validation, status codes, stored fields. No code. | J14: Not started | M14: =HYPERLINK("WEEKS/WEEK_02.md","Week 2 · Day 13")
A15: 14 | B15: =START!$B$4+A15-1 | C15: =TEXT(B15,"ddd") | D15: 2 | E15: Foundations | F15: Weekly test, review, project, stories | H15: Re-solve Two Sum cold. Then explain Range Sum Query (303) from Saturday: derive prefix[r+1] − prefix[l] on paper, includ | J15: Not started | M15: =HYPERLINK("WEEKS/WEEK_02.md","Week 2 · Day 14")
A16: 15 | B16: =START!$B$4+A16-1 | C16: =TEXT(B16,"ddd") | D16: 3 | E16: Foundations | F16: String traversal and frequency | G16: Valid Anagram, Ransom Note | H16: Strings: immutability, interning, StringBuilder, why concatenation in a loop is O(n²) | I16: Why is string concatenation in a loop O(n²)? | J16: Not started | M16: =HYPERLINK("WEEKS/WEEK_03.md","Week 3 · Day 15")
A17: 16 | B17: =START!$B$4+A17-1 | C17: =TEXT(B17,"ddd") | D17: 3 | E17: Foundations | F17: Opposite-end pointers | G17: Valid Palindrome, Valid Palindrome II | H17: Classes, constructors and chaining, fields vs properties, the six access modifiers | I17: What is the job of a constructor? | J17: Not started | M17: =HYPERLINK("WEEKS/WEEK_03.md","Week 3 · Day 16")
A18: 17 | B18: =START!$B$4+A18-1 | C18: =TEXT(B18,"ddd") | D18: 3 | E18: Foundations | F18: Pointers on sorted input | G18: Two Sum II - Input Array Is Sorted, Squares of a Sorted Array | H18: virtual / override / new; interface vs abstract class | I18: Interface or abstract class — how do you decide? | J18: Not started | M18: =HYPERLINK("WEEKS/WEEK_03.md","Week 3 · Day 17")
A19: 18 | B19: =START!$B$4+A19-1 | C19: =TEXT(B19,"ddd") | D19: 3 | E19: Foundations | F19: Fixed-size windows | G19: Maximum Average Subarray I, Longest Common Prefix | H19: Composition over inheritance; generics, constraints and variance; generics vs Java erasure | I19: Why composition over inheritance? | J19: Not started | M19: =HYPERLINK("WEEKS/WEEK_03.md","Week 3 · Day 18")
A20: 19 | B20: =START!$B$4+A20-1 | C20: =TEXT(B20,"ddd") | D20: 3 | E20: Foundations | F20: Repair and retrieval | G20: re-solves + Reverse String | H20: re-explain the week | J20: Not started | M20: =HYPERLINK("WEEKS/WEEK_03.md","Week 3 · Day 19")
A21: 20 | B21: =START!$B$4+A21-1 | C21: =TEXT(B21,"ddd") | D21: 3 | E21: Foundations | F21: Deep work: DSA + design + lab/project | G21: First Unique Character in a String, Isomorphic Strings, Word Pattern, 3Sum | H21: URL shortener — requirements only: 3 functional requirements, 3 constraints, the redirect API. Single server. Read the c | J21: Not started | M21: =HYPERLINK("WEEKS/WEEK_03.md","Week 3 · Day 20")
A22: 21 | B22: =START!$B$4+A22-1 | C22: =TEXT(B22,"ddd") | D22: 3 | E22: Foundations | F22: Weekly test, review, project, stories | H22: Implement IComparable<T> and IEquatable<T> on a Money record; sort a list of jobs by priority with a custom IComparer. | J22: Not started | M22: =HYPERLINK("WEEKS/WEEK_03.md","Week 3 · Day 21")
A23: 22 | B23: =START!$B$4+A23-1 | C23: =TEXT(B23,"ddd") | D23: 4 | E23: Foundations | F23: Window validity and shrink rules | G23: Longest Substring Without Repeating Characters | H23: IEnumerable vs ICollection vs IList vs IQueryable; what yield return compiles into | I23: IEnumerable vs IQueryable — why does it matter for a database query? | J23: Not started | M23: =HYPERLINK("WEEKS/WEEK_04.md","Week 4 · Day 22")
A24: 23 | B24: =START!$B$4+A24-1 | C24: =TEXT(B24,"ddd") | D24: 4 | E24: Foundations | F24: Monotone windows and their limits | G24: Minimum Size Subarray Sum, Max Consecutive Ones III | H24: Deferred execution and LINQ costs | I24: What is deferred execution and give one bug it causes. | J24: Not started | M24: =HYPERLINK("WEEKS/WEEK_04.md","Week 4 · Day 23")
A25: 24 | B25: =START!$B$4+A25-1 | C25: =TEXT(B25,"ddd") | D25: 4 | E25: Foundations | F25: Prefix sums plus a frequency map | G25: Subarray Sum Equals K | H25: Delegates, lambdas, closures and events | I25: What does a closure allocate, and what is the loop-variable trap? | J25: Not started | M25: =HYPERLINK("WEEKS/WEEK_04.md","Week 4 · Day 24")
A26: 25 | B26: =START!$B$4+A26-1 | C26: =TEXT(B26,"ddd") | D26: 4 | E26: Foundations | F26: Local and global optimum (Kadane) | G26: Best Time to Buy and Sell Stock, Maximum Subarray | H26: Exceptions: throw vs throw ex, filters, cost, using and IDisposable basics | I26: What is the difference between throw and throw ex? | J26: Not started | M26: =HYPERLINK("WEEKS/WEEK_04.md","Week 4 · Day 25")
A27: 26 | B27: =START!$B$4+A27-1 | C27: =TEXT(B27,"ddd") | D27: 4 | E27: Foundations | F27: Repair and retrieval | G27: re-solves + Contains Duplicate II | H27: re-explain the week | J27: Not started | M27: =HYPERLINK("WEEKS/WEEK_04.md","Week 4 · Day 26")
A28: 27 | B28: =START!$B$4+A28-1 | C28: =TEXT(B28,"ddd") | D28: 4 | E28: Foundations | F28: Deep work: DSA + design + lab/project | G28: Product of Array Except Self, Longest Repeating Character Replacement, Permutation in String, Group Anagrams | H28: URL shortener — data model and key generation (base62 counter vs hash), a cache, and a request-rate estimate. Still one | J28: Not started | M28: =HYPERLINK("WEEKS/WEEK_04.md","Week 4 · Day 27")
A29: 28 | B29: =START!$B$4+A29-1 | C29: =TEXT(B29,"ddd") | D29: 4 | E29: Foundations | F29: Month 1 checkpoint | H29: Month 1 test (see checkpoint below). Then repair the weakest prerequisite you found. | J29: Not started | M29: =HYPERLINK("WEEKS/WEEK_04.md","Week 4 · Day 28")
A30: 29 | B30: =START!$B$4+A30-1 | C30: =TEXT(B30,"ddd") | D30: 5 | E30: Foundations | F30: Binary search invariant | G30: Binary Search, Search Insert Position | H30: IDisposable, using, the dispose pattern and finalizers | I30: Why does a finalizer make collection take (at least) two GC cycles? | J30: Not started | M30: =HYPERLINK("WEEKS/WEEK_05.md","Week 5 · Day 29")
A31: 30 | B31: =START!$B$4+A31-1 | C31: =TEXT(B31,"ddd") | D31: 5 | E31: Foundations | F31: Lower and upper bounds | G31: Find First and Last Position of Element in Sorted Array, First Bad Version | H31: GC generations, the large object heap, workstation vs server GC | I31: Why is a gen 0 collection cheap and a gen 2 collection expensive? | J31: Not started | M31: =HYPERLINK("WEEKS/WEEK_05.md","Week 5 · Day 30")
A32: 31 | B32: =START!$B$4+A32-1 | C32: =TEXT(B32,"ddd") | D32: 5 | E32: Foundations | F32: Rotated sorted arrays | G32: Find Minimum in Rotated Sorted Array, Search in Rotated Sorted Array | H32: async/await: what await does and the generated state machine | I32: What does await actually do? | J32: Not started | M32: =HYPERLINK("WEEKS/WEEK_05.md","Week 5 · Day 31")
A33: 32 | B33: =START!$B$4+A33-1 | C33: =TEXT(B33,"ddd") | D33: 5 | E33: Foundations | F33: Binary search on the answer | G33: Koko Eating Bananas, Capacity To Ship Packages Within D Days | H33: async pitfalls: async void, .Result deadlock, ConfigureAwait, ValueTask, CancellationToken | I33: Why does calling .Result deadlock in an app with a synchronization context? | J33: Not started | M33: =HYPERLINK("WEEKS/WEEK_05.md","Week 5 · Day 32")
A34: 33 | B34: =START!$B$4+A34-1 | C34: =TEXT(B34,"ddd") | D34: 5 | E34: Foundations | F34: Repair and retrieval | G34: re-solves + Sqrt(x) | H34: re-explain the week | J34: Not started | M34: =HYPERLINK("WEEKS/WEEK_05.md","Week 5 · Day 33")
A35: 34 | B35: =START!$B$4+A35-1 | C35: =TEXT(B35,"ddd") | D35: 5 | E35: Foundations | F35: Deep work: DSA + design + lab/project | G35: Implement merge sort (stable, O(n log n), O(n) extra), Implement quicksort partition (Lomuto and Hoare) and quickselect, Sort an Array, Sort Colors | H35: URL shortener — full 30-minute design: requirements, estimate, API, schema and indexes, cache, one failure (cache down). | J35: Not started | M35: =HYPERLINK("WEEKS/WEEK_05.md","Week 5 · Day 34")
A36: 35 | B36: =START!$B$4+A36-1 | C36: =TEXT(B36,"ddd") | D36: 5 | E36: Foundations | F36: Weekly test, review, project, stories | H36: Read Stephen Toub's 'How Async/Await Really Works in C#' (devblogs.microsoft.com) for 60 minutes; write a six-question s | J36: Not started | M36: =HYPERLINK("WEEKS/WEEK_05.md","Week 5 · Day 35")
A37: 36 | B37: =START!$B$4+A37-1 | C37: =TEXT(B37,"ddd") | D37: 6 | E37: Foundations | F37: Linked-list reference mutation | G37: Reverse Linked List, Middle of the Linked List | H37: OS vocabulary; process vs thread vs Task; the thread pool and starvation | I37: What is thread-pool starvation and how would you spot it? | J37: Not started | M37: =HYPERLINK("WEEKS/WEEK_06.md","Week 6 · Day 36")
A38: 37 | B38: =START!$B$4+A38-1 | C38: =TEXT(B38,"ddd") | D38: 6 | E38: Foundations | F38: Dummy node and merging | G38: Merge Two Sorted Lists, Remove Nth Node From End of List | H38: Race conditions, lock, Interlocked, volatile | I38: What is a race condition at the memory level? | J38: Not started | M38: =HYPERLINK("WEEKS/WEEK_06.md","Week 6 · Day 37")
A39: 38 | B39: =START!$B$4+A39-1 | C39: =TEXT(B39,"ddd") | D39: 6 | E39: Foundations | F39: Cycles and palindromes | G39: Linked List Cycle, Palindrome Linked List | H39: Deadlock, why not await inside lock, SemaphoreSlim vs Mutex vs ReaderWriterLockSlim | I39: What causes a deadlock and how do you prevent one? | J39: Not started | M39: =HYPERLINK("WEEKS/WEEK_06.md","Week 6 · Day 38")
A40: 39 | B40: =START!$B$4+A40-1 | C40: =TEXT(B40,"ddd") | D40: 6 | E40: Foundations | F40: Stack and queue contracts | G40: Valid Parentheses, Implement Queue using Stacks | H40: Channel<T>, Parallel.For/PLINQ; your email pipeline as a concurrency story | I40: When does Parallel.For hurt rather than help? | J40: Not started | M40: =HYPERLINK("WEEKS/WEEK_06.md","Week 6 · Day 39")
A41: 40 | B41: =START!$B$4+A41-1 | C41: =TEXT(B41,"ddd") | D41: 6 | E41: Foundations | F41: Repair and retrieval | G41: re-solves + Intersection of Two Linked Lists | H41: re-explain the week | J41: Not started | M41: =HYPERLINK("WEEKS/WEEK_06.md","Week 6 · Day 40")
A42: 41 | B42: =START!$B$4+A42-1 | C42: =TEXT(B42,"ddd") | D42: 6 | E42: Foundations | F42: Deep work: DSA + design + lab/project | G42: Min Stack, Evaluate Reverse Polish Notation, Reorder List, Add Two Numbers | H42: LLD: logging framework — levels, sinks (console, file, in-memory), formatting, async buffering. Requirements → classes → | J42: Not started | M42: =HYPERLINK("WEEKS/WEEK_06.md","Week 6 · Day 41")
A43: 42 | B43: =START!$B$4+A43-1 | C43: =TEXT(B43,"ddd") | D43: 6 | E43: Foundations | F43: Weekly test, review, project, stories | H43: Implement the logger from Saturday's design: console + in-memory sinks, levels, and tests. Add a new sink without changi | J43: Not started | M43: =HYPERLINK("WEEKS/WEEK_06.md","Week 6 · Day 42")
A44: 43 | B44: =START!$B$4+A44-1 | C44: =TEXT(B44,"ddd") | D44: 7 | E44: Foundations | F44: Recursion mechanics | G44: Recursive sum, factorial, power, reverse a string — draw the call stack, Fibonacci three ways: naive recursion, memo, iterative — compare cost, Fibonacci Number | H44: .NET Framework vs .NET Core vs modern .NET; CLR, SDK, BCL; JIT, tiered compilation, ReadyToRun, AOT | I44: .NET Framework vs modern .NET in sixty seconds. | J44: Not started | M44: =HYPERLINK("WEEKS/WEEK_07.md","Week 7 · Day 43")
A45: 44 | B45: =START!$B$4+A45-1 | C45: =TEXT(B45,"ddd") | D45: 7 | E45: Foundations | F45: Choose, explore, unchoose | G45: Subsets, Pow(x, n) | H45: GC gen 0 vs gen 2, the LOH; trace a request from Kestrel to your endpoint and back | I45: Trace a request from Kestrel to your controller and back. | J45: Not started | M45: =HYPERLINK("WEEKS/WEEK_07.md","Week 7 · Day 44")
A46: 45 | B46: =START!$B$4+A46-1 | C46: =TEXT(B46,"ddd") | D46: 7 | E46: Foundations | F46: Permutations | G46: Permutations, Letter Combinations of a Phone Number | H46: Middleware order (with the CORS correction) and DI lifetimes / captive dependencies | I46: Explain DI lifetimes and the captive dependency problem. | J46: Not started | M46: =HYPERLINK("WEEKS/WEEK_07.md","Week 7 · Day 45")
A47: 46 | B47: =START!$B$4+A47-1 | C47: =TEXT(B47,"ddd") | D47: 7 | E47: Foundations | F47: Pruning and repeated candidates | G47: Combination Sum, Generate Parentheses | H47: Configuration precedence, IOptions, validation and ProblemDetails | I47: How does configuration precedence work? | J47: Not started | M47: =HYPERLINK("WEEKS/WEEK_07.md","Week 7 · Day 46")
A48: 47 | B48: =START!$B$4+A48-1 | C48: =TEXT(B48,"ddd") | D48: 7 | E48: Foundations | F48: Repair and retrieval | G48: re-solves + Combination Sum III | H48: re-explain the week | J48: Not started | M48: =HYPERLINK("WEEKS/WEEK_07.md","Week 7 · Day 47")
A49: 48 | B49: =START!$B$4+A49-1 | C49: =TEXT(B49,"ddd") | D49: 7 | E49: Foundations | F49: Deep work: DSA + design + lab/project | G49: Subsets II, Permutations II, Word Search, Palindrome Partitioning | H49: LLD: parking lot — requirements, vehicle and spot types, allocation strategy, ticket and payment, state changes. Sequent | J49: Not started | M49: =HYPERLINK("WEEKS/WEEK_07.md","Week 7 · Day 48")
A50: 49 | B50: =START!$B$4+A50-1 | C50: =TEXT(B50,"ddd") | D50: 7 | E50: Foundations | F50: Weekly test, review, project, stories | H50: Reproduce a captive dependency in the API (scoped DbContext-like service inside a singleton), see the bug, fix it with I | J50: Not started | M50: =HYPERLINK("WEEKS/WEEK_07.md","Week 7 · Day 49")
A51: 50 | B51: =START!$B$4+A51-1 | C51: =TEXT(B51,"ddd") | D51: 8 | E51: Foundations | F51: Tree recursion | G51: Maximum Depth of Binary Tree, Invert Binary Tree, Same Tree | H51: HTTP and REST: methods, idempotency, status codes, versioning | I51: Which HTTP methods are idempotent, and why does it matter? | J51: Not started | M51: =HYPERLINK("WEEKS/WEEK_08.md","Week 8 · Day 50")
A52: 51 | B52: =START!$B$4+A52-1 | C52: =TEXT(B52,"ddd") | D52: 8 | E52: Foundations | F52: Level-order BFS | G52: Binary Tree Level Order Traversal, Binary Tree Right Side View | H52: JWT: structure, signing vs encryption, validation, revocation; authentication vs authorization | I52: What is inside a JWT, and what is the difference between signing and encryption? | J52: Not started | M52: =HYPERLINK("WEEKS/WEEK_08.md","Week 8 · Day 51")
A53: 52 | B53: =START!$B$4+A53-1 | C53: =TEXT(B53,"ddd") | D53: 8 | E53: Foundations | F53: BST global invariant | G53: Validate Binary Search Tree, Kth Smallest Element in a BST | H53: EF Core change tracker, AsNoTracking, projections, N+1 | I53: What is the N+1 problem, how do you find it, and how do you fix it? | J53: Not started | M53: =HYPERLINK("WEEKS/WEEK_08.md","Week 8 · Day 52")
A54: 53 | B54: =START!$B$4+A54-1 | C54: =TEXT(B54,"ddd") | D54: 8 | E54: Foundations | F54: Subtree combination and BST LCA | G54: Diameter of Binary Tree, Balanced Binary Tree, Lowest Common Ancestor of a Binary Search Tree | H54: Cache-aside vs write-through vs write-behind, stampede, BackgroundService | I54: Compare cache-aside, write-through and write-behind. | J54: Not started | M54: =HYPERLINK("WEEKS/WEEK_08.md","Week 8 · Day 53")
A55: 54 | B55: =START!$B$4+A55-1 | C55: =TEXT(B55,"ddd") | D55: 8 | E55: Foundations | F55: Repair and retrieval | G55: re-solves + Subtree of Another Tree | H55: re-explain the week | J55: Not started | M55: =HYPERLINK("WEEKS/WEEK_08.md","Week 8 · Day 54")
A56: 55 | B56: =START!$B$4+A56-1 | C56: =TEXT(B56,"ddd") | D56: 8 | E56: Foundations | F56: Deep work: DSA + design + lab/project | G56: Lowest Common Ancestor of a Binary Tree, Construct Binary Tree from Preorder and Inorder Traversal, Path Sum, Count Good Nodes in Binary Tree | H56: FIRST DESIGN MOCK (45 minutes, timer on, talk aloud, ideally with a partner): URL shortener from a blank page. Score you | J56: Not started | M56: =HYPERLINK("WEEKS/WEEK_08.md","Week 8 · Day 55")
A57: 56 | B57: =START!$B$4+A57-1 | C57: =TEXT(B57,"ddd") | D57: 8 | E57: Foundations | F57: Month 2 checkpoint | H57: Month 2 test (see checkpoint). Then repair the weakest item. | J57: Not started | M57: =HYPERLINK("WEEKS/WEEK_08.md","Week 8 · Day 56")
A58: 57 | B58: =START!$B$4+A58-1 | C58: =TEXT(B58,"ddd") | D58: 9 | E58: Core depth and the project starts | F58: Heap invariant and PriorityQueue | G58: Kth Largest Element in an Array, Last Stone Weight | H58: SQL basics and data modeling: keys, constraints, normalization, when to denormalise | I58: When would you denormalise on purpose? | J58: Not started | M58: =HYPERLINK("WEEKS/WEEK_09.md","Week 9 · Day 57")
A59: 58 | B59: =START!$B$4+A59-1 | C59: =TEXT(B59,"ddd") | D59: 9 | E59: Core depth and the project starts | F59: Frequency plus top-K | G59: Top K Frequent Elements, K Closest Points to Origin | H59: How data is stored; indexes, write cost, covering indexes | I59: Why does an index make reads faster and writes slower? | J59: Not started | M59: =HYPERLINK("WEEKS/WEEK_09.md","Week 9 · Day 58")
A60: 59 | B60: =START!$B$4+A60-1 | C60: =TEXT(B60,"ddd") | D60: 9 | E60: Core depth and the project starts | F60: K-way merging | G60: Merge k Sorted Lists, Task Scheduler | H60: Execution plans, seek vs scan vs lookup, SARGability, join algorithms | I60: Why can WHERE YEAR(created) = 2026 not use an index? | J60: Not started | M60: =HYPERLINK("WEEKS/WEEK_09.md","Week 9 · Day 59")
A61: 60 | B61: =START!$B$4+A61-1 | C61: =TEXT(B61,"ddd") | D61: 9 | E61: Core depth and the project starts | F61: Two heaps and selection without full sort | G61: Find Median from Data Stream, Implement quicksort partition (Lomuto and Hoare) and quickselect | H61: Logical execution order, window functions, CTEs, connection pooling | I61: What is the logical execution order of a SQL statement? | J61: Not started | M61: =HYPERLINK("WEEKS/WEEK_09.md","Week 9 · Day 60")
A62: 61 | B62: =START!$B$4+A62-1 | C62: =TEXT(B62,"ddd") | D62: 9 | E62: Core depth and the project starts | F62: Repair and retrieval | G62: re-solves + Kth Largest Element in a Stream | H62: re-explain the week | J62: Not started | M62: =HYPERLINK("WEEKS/WEEK_09.md","Week 9 · Day 61")
A63: 62 | B63: =START!$B$4+A63-1 | C63: =TEXT(B63,"ddd") | D63: 9 | E63: Core depth and the project starts | F63: Deep work: DSA + design + lab/project | G63: Top K Frequent Words, Reorganize String, Sort Characters By Frequency, Implement a binary min-heap (push, pop, heapify) on an array | H63: LLD: LRU cache — Dictionary + doubly linked list, O(1) get and put; then thread safety (one lock vs ReaderWriterLockSlim | J63: Not started | M63: =HYPERLINK("WEEKS/WEEK_09.md","Week 9 · Day 62")
A64: 63 | B64: =START!$B$4+A64-1 | C64: =TEXT(B64,"ddd") | D64: 9 | E64: Core depth and the project starts | F64: Weekly test, review, project, stories | H64: Finish all 20 practice queries; check your answers; put any you missed on the WEAK sheet. Implement LRU Cache (146) from | J64: Not started | M64: =HYPERLINK("WEEKS/WEEK_09.md","Week 9 · Day 63")
A65: 64 | B65: =START!$B$4+A65-1 | C65: =TEXT(B65,"ddd") | D65: 10 | E65: Core depth and the project starts | F65: Graph representation and DFS | G65: Number of Islands, Flood Fill | H65: Transactions, ACID, anomalies, isolation levels | I65: State the four ACID properties and what each protects. | J65: Not started | M65: =HYPERLINK("WEEKS/WEEK_10.md","Week 10 · Day 64")
A66: 65 | B66: =START!$B$4+A66-1 | C66: =TEXT(B66,"ddd") | D66: 10 | E66: Core depth and the project starts | F66: Graph identity and copying | G66: Clone Graph, Max Area of Island | H66: Write skew, snapshot isolation, MVCC vs locking | I66: What is write skew, and why does snapshot isolation permit it? | J66: Not started | M66: =HYPERLINK("WEEKS/WEEK_10.md","Week 10 · Day 65")
A67: 66 | B67: =START!$B$4+A67-1 | C67: =TEXT(B67,"ddd") | D67: 10 | E67: Core depth and the project starts | F67: Multi-source BFS | G67: Rotting Oranges, 01 Matrix | H67: Locks, deadlocks, lock escalation, optimistic vs pessimistic concurrency | I67: Optimistic or pessimistic locking — when each? | J67: Not started | M67: =HYPERLINK("WEEKS/WEEK_10.md","Week 10 · Day 66")
A68: 67 | B68: =START!$B$4+A68-1 | C68: =TEXT(B68,"ddd") | D68: 10 | E68: Core depth and the project starts | F68: Reachability with reversed reasoning | G68: Pacific Atlantic Water Flow, Surrounded Regions | H68: Safe migrations, CDC, backup and restore | I68: How do you change a schema without downtime? | J68: Not started | M68: =HYPERLINK("WEEKS/WEEK_10.md","Week 10 · Day 67")
A69: 68 | B69: =START!$B$4+A69-1 | C69: =TEXT(B69,"ddd") | D69: 10 | E69: Core depth and the project starts | F69: Repair and retrieval | G69: re-solves + Find if Path Exists in Graph | H69: re-explain the week | J69: Not started | M69: =HYPERLINK("WEEKS/WEEK_10.md","Week 10 · Day 68")
A70: 69 | B70: =START!$B$4+A70-1 | C70: =TEXT(B70,"ddd") | D70: 10 | E70: Core depth and the project starts | F70: Deep work: DSA + design + lab/project | G70: Word Ladder, Is Graph Bipartite?, Walls and Gates, Keys and Rooms | H70: Distributed rate limiter HLD: fixed window vs sliding window vs token bucket; atomic updates in Redis; per-tenant keys; | J70: Not started | M70: =HYPERLINK("WEEKS/WEEK_10.md","Week 10 · Day 69")
A71: 70 | B71: =START!$B$4+A71-1 | C71: =TEXT(B71,"ddd") | D71: 10 | E71: Core depth and the project starts | F71: Weekly test, review, project, stories | H71: Do a SQL Server dirty-read demo (READ UNCOMMITTED / NOLOCK) if you have SQL Server; note PostgreSQL can never show one. | J71: Not started | M71: =HYPERLINK("WEEKS/WEEK_10.md","Week 10 · Day 70")
A72: 71 | B72: =START!$B$4+A72-1 | C72: =TEXT(B72,"ddd") | D72: 11 | E72: Core depth and the project starts | F72: Directed cycles | G72: Course Schedule | H72: What happens when you type a URL; DNS resolution | I72: What happens when you type a URL and press enter? (5-minute version) | J72: Not started | M72: =HYPERLINK("WEEKS/WEEK_11.md","Week 11 · Day 71")
A73: 72 | B73: =START!$B$4+A73-1 | C73: =TEXT(B73,"ddd") | D73: 11 | E73: Core depth and the project starts | F73: Topological ordering | G73: Course Schedule II | H73: TCP handshake, flow vs congestion control, head-of-line blocking, HTTP/2 and HTTP/3 | I73: Flow control or congestion control — what is the difference? | J73: Not started | M73: =HYPERLINK("WEEKS/WEEK_11.md","Week 11 · Day 72")
A74: 73 | B74: =START!$B$4+A74-1 | C74: =TEXT(B74,"ddd") | D74: 11 | E74: Core depth and the project starts | F74: Disjoint set union | G74: Implement DSU: find with path compression, union by rank/size, Redundant Connection, Number of Provinces | H74: TLS, what HTTPS does not protect, CORS and preflight, WebSockets | I74: Explain CORS and preflight (with the corrected middleware order). | J74: Not started | M74: =HYPERLINK("WEEKS/WEEK_11.md","Week 11 · Day 73")
A75: 74 | B75: =START!$B$4+A75-1 | C75: =TEXT(B75,"ddd") | D75: 11 | E75: Core depth and the project starts | F75: Connectivity by shared identity | G75: Accounts Merge | H75: OS: process vs thread, context switches, virtual memory | I75: Why is a context switch expensive? | J75: Not started | M75: =HYPERLINK("WEEKS/WEEK_11.md","Week 11 · Day 74")
A76: 75 | B76: =START!$B$4+A76-1 | C76: =TEXT(B76,"ddd") | D76: 11 | E76: Core depth and the project starts | F76: Repair and retrieval | G76: re-solves + Find Eventual Safe States | H76: re-explain the week | J76: Not started | M76: =HYPERLINK("WEEKS/WEEK_11.md","Week 11 · Day 75")
A77: 76 | B77: =START!$B$4+A77-1 | C77: =TEXT(B77,"ddd") | D77: 11 | E77: Core depth and the project starts | F77: Deep work: DSA + design + lab/project | G77: Alien Dictionary, Graph Valid Tree, Number of Connected Components in an Undirected Graph, Minimum Height Trees | H77: Job platform HLD v1 (your project): requirements, acceptance vs completion latency, API, schema, durable state machine, | J77: Not started | M77: =HYPERLINK("WEEKS/WEEK_11.md","Week 11 · Day 76")
A78: 77 | B78: =START!$B$4+A78-1 | C78: =TEXT(B78,"ddd") | D78: 11 | E78: Core depth and the project starts | F78: Weekly test, review, project, stories | H78: PROJECT M1 — finish and prove the acceptance test: restart the API and read the job back; integration test for an illega | J78: Not started | M78: =HYPERLINK("WEEKS/WEEK_11.md","Week 11 · Day 77")
A79: 78 | B79: =START!$B$4+A79-1 | C79: =TEXT(B79,"ddd") | D79: 12 | E79: Core depth and the project starts | F79: Weighted shortest path | G79: Network Delay Time | H79: OS scheduler vs .NET scheduler; mutex, semaphore, spinlock; async I/O without a thread | I79: Why does async I/O not need a thread while waiting? | J79: Not started | M79: =HYPERLINK("WEEKS/WEEK_12.md","Week 12 · Day 78")
A80: 79 | B80: =START!$B$4+A80-1 | C80: =TEXT(B80,"ddd") | D80: 12 | E80: Core depth and the project starts | F80: Sort and merge intervals | G80: Merge Intervals, Insert Interval | H80: Delivery guarantees, exactly-once processing, visibility timeouts | I80: Explain the delivery guarantees, and how you get exactly-once *processing*. | J80: Not started | M80: =HYPERLINK("WEEKS/WEEK_12.md","Week 12 · Day 79")
A81: 80 | B81: =START!$B$4+A81-1 | C81: =TEXT(B81,"ddd") | D81: 12 | E81: Core depth and the project starts | F81: Greedy interval scheduling | G81: Non-overlapping Intervals, Minimum Number of Arrows to Burst Balloons, Meeting Rooms II | H81: Retries with jitter, DLQ, SQS vs RabbitMQ vs Kafka | I81: SQS, RabbitMQ or Kafka — how do you choose? | J81: Not started | M81: =HYPERLINK("WEEKS/WEEK_12.md","Week 12 · Day 80")
A82: 81 | B82: =START!$B$4+A82-1 | C82: =TEXT(B82,"ddd") | D82: 12 | E82: Core depth and the project starts | F82: Reachability with greedy state | G82: Jump Game, Gas Station | H82: Kafka partitions and ordering, backpressure, the outbox pattern; HttpClient lifetime | I82: What is the outbox pattern and what problem does it solve? | J82: Not started | M82: =HYPERLINK("WEEKS/WEEK_12.md","Week 12 · Day 81")
A83: 82 | B83: =START!$B$4+A83-1 | C83: =TEXT(B83,"ddd") | D83: 12 | E83: Core depth and the project starts | F83: Repair and retrieval | G83: re-solves + Path With Minimum Effort | H83: re-explain the week | J83: Not started | M83: =HYPERLINK("WEEKS/WEEK_12.md","Week 12 · Day 82")
A84: 83 | B84: =START!$B$4+A84-1 | C84: =TEXT(B84,"ddd") | D84: 12 | E84: Core depth and the project starts | F84: Deep work: DSA + design + lab/project | G84: Cheapest Flights Within K Stops, Min Cost to Connect All Points, Jump Game II, Partition Labels | H84: Notification service HLD: channels and preferences, async delivery through queues, retries per channel, duplicate preven | J84: Not started | M84: =HYPERLINK("WEEKS/WEEK_12.md","Week 12 · Day 83")
A85: 84 | B85: =START!$B$4+A85-1 | C85: =TEXT(B85,"ddd") | D85: 12 | E85: Core depth and the project starts | F85: Month 3 checkpoint | H85: Month 3 test (see checkpoint). Then finish PROJECT M2: stop the worker in the middle of a job and show the message is re | J85: Not started | M85: =HYPERLINK("WEEKS/WEEK_12.md","Week 12 · Day 84")
A86: 85 | B86: =START!$B$4+A86-1 | C86: =TEXT(B86,"ddd") | D86: 13 | E86: Core depth and the project starts | F86: From recursion to DP | G86: Climbing Stairs, Min Cost Climbing Stairs | H86: Replication, read-your-writes, quorum, split brain | I86: Why can a read replica serve stale data, and how do you hide that from a user? | J86: Not started | M86: =HYPERLINK("WEEKS/WEEK_13.md","Week 13 · Day 85")
A87: 86 | B87: =START!$B$4+A87-1 | C87: =TEXT(B87,"ddd") | D87: 13 | E87: Core depth and the project starts | F87: Take or skip | G87: House Robber, House Robber II, N-th Tribonacci Number | H87: Consistent hashing, sharding, hot keys, CAP and PACELC, consistency models | I87: What does CAP actually say, and what is the common misreading? | J87: Not started | M87: =HYPERLINK("WEEKS/WEEK_13.md","Week 13 · Day 86")
A88: 87 | B88: =START!$B$4+A88-1 | C88: =TEXT(B88,"ddd") | D88: 13 | E88: Core depth and the project starts | F88: Unbounded choices | G88: Coin Change, Decode Ways | H88: Redis, eviction (LRU/LFU/TTL), cache patterns, invalidation, stampede | I88: Why is Redis being single-threaded a feature? | J88: Not started | M88: =HYPERLINK("WEEKS/WEEK_13.md","Week 13 · Day 87")
A89: 88 | B89: =START!$B$4+A89-1 | C89: =TEXT(B89,"ddd") | D89: 13 | E89: Core depth and the project starts | F89: Segmentation and subsequences | G89: Word Break, Longest Increasing Subsequence | H89: Scaling fundamentals: vertical vs horizontal, stateless, load balancers L4/L7, gateways, discovery, DNS load balancing, CDN | I89: L4 vs L7 load balancer? | J89: Not started | M89: =HYPERLINK("WEEKS/WEEK_13.md","Week 13 · Day 88")
A90: 89 | B90: =START!$B$4+A90-1 | C90: =TEXT(B90,"ddd") | D90: 13 | E90: Core depth and the project starts | F90: Repair and retrieval | G90: re-solves + Combination Sum IV | H90: re-explain the week | J90: Not started | M90: =HYPERLINK("WEEKS/WEEK_13.md","Week 13 · Day 89")
A91: 90 | B91: =START!$B$4+A91-1 | C91: =TEXT(B91,"ddd") | D91: 13 | E91: Core depth and the project starts | F91: Deep work: DSA + design + lab/project | G91: Maximum Product Subarray, Longest Palindromic Substring, Palindromic Substrings, Combination Sum IV | H91: LLD: split-expense service (Splitwise) — users, groups, expenses, split types (equal, exact, percent), balances, simplif | J91: Not started | M91: =HYPERLINK("WEEKS/WEEK_13.md","Week 13 · Day 90")
A92: 91 | B92: =START!$B$4+A92-1 | C92: =TEXT(B92,"ddd") | D92: 13 | E92: Core depth and the project starts | F92: Weekly test, review, project, stories | H92: Finish PROJECT M3 and write its decision record (why outbox, polling vs CDC, ordering). | J92: Not started | M92: =HYPERLINK("WEEKS/WEEK_13.md","Week 13 · Day 91")
A93: 92 | B93: =START!$B$4+A93-1 | C93: =TEXT(B93,"ddd") | D93: 14 | E93: Core depth and the project starts | F93: 0/1 decisions | G93: 0/1 knapsack (classic) — derive state, then 1-D array looping backwards, Partition Equal Subset Sum, Subset sum (boolean DP) | H93: SOLID: single responsibility and open/closed | I93: Explain Single Responsibility without reciting the definition. | J93: Not started | M93: =HYPERLINK("WEEKS/WEEK_14.md","Week 14 · Day 92")
A94: 93 | B94: =START!$B$4+A94-1 | C94: =TEXT(B94,"ddd") | D94: 14 | E94: Core depth and the project starts | F94: Counting: combinations vs permutations | G94: Coin Change II, Target Sum | H94: Liskov, Interface Segregation, Dependency Inversion; when a pattern is over-engineering | I94: Why is Dependency Inversion not the same as using a DI container? | J94: Not started | M94: =HYPERLINK("WEEKS/WEEK_14.md","Week 14 · Day 93")
A95: 94 | B95: =START!$B$4+A95-1 | C95: =TEXT(B95,"ddd") | D95: 14 | E95: Core depth and the project starts | F95: Grid paths | G95: Unique Paths, Unique Paths II, Minimum Path Sum | H95: Strategy vs switch, event-handler leaks, Decorator vs inheritance; the 23 GoF patterns | I95: Decorator or inheritance? | J95: Not started | M95: =HYPERLINK("WEEKS/WEEK_14.md","Week 14 · Day 94")
A96: 95 | B96: =START!$B$4+A96-1 | C96: =TEXT(B96,"ddd") | D96: 14 | E96: Core depth and the project starts | F96: More knapsack shapes | G96: Ones and Zeroes, Perfect Squares, Last Stone Weight II | H96: Repository over EF Core, Singleton, anti-patterns, testability | I96: Why is untestable code usually badly designed code? | J96: Not started | M96: =HYPERLINK("WEEKS/WEEK_14.md","Week 14 · Day 95")
A97: 96 | B97: =START!$B$4+A97-1 | C97: =TEXT(B97,"ddd") | D97: 14 | E97: Core depth and the project starts | F97: Repair and retrieval | G97: re-solves + Triangle | H97: re-explain the week | J97: Not started | M97: =HYPERLINK("WEEKS/WEEK_14.md","Week 14 · Day 96")
A98: 97 | B98: =START!$B$4+A98-1 | C98: =TEXT(B98,"ddd") | D98: 14 | E98: Core depth and the project starts | F98: Deep work: DSA + design + lab/project | G98: Triangle, Maximal Square, Count Square Submatrices with All Ones, Coin Change | H98: LLD: rate limiter with a controllable clock — token bucket class, per-client policy, TimeProvider/FakeTimeProvider in te | J98: Not started | M98: =HYPERLINK("WEEKS/WEEK_14.md","Week 14 · Day 97")
A99: 98 | B99: =START!$B$4+A99-1 | C99: =TEXT(B99,"ddd") | D99: 14 | E99: Core depth and the project starts | F99: Weekly test, review, project, stories | H99: Finish PROJECT M4 tests. Write down exactly where the guarantee stops (external effects). | J99: Not started | M99: =HYPERLINK("WEEKS/WEEK_14.md","Week 14 · Day 98")
A100: 99 | B100: =START!$B$4+A100-1 | C100: =TEXT(B100,"ddd") | D100: 15 | E100: Core depth and the project starts | F100: Two-string state | G100: Longest Common Subsequence | H100: Authentication vs authorization; JWT validation and negative tests | I100: Why is 'authenticated' not the same as 'authorized'? | J100: Not started | M100: =HYPERLINK("WEEKS/WEEK_15.md","Week 15 · Day 99")
...

Sheet DSA_LOG
A1: Planned day | B1: Problem | C1: Difficulty | D1: Pattern | E1: Result | F1: Solved on | G1: Brute force | H1: Insight (one sentence) | I1: Invariant | J1: Time / space | K1: One variation | L1: Re-solve D+1 | M1: D+3 | N1: D+7 | O1: D+14 | P1: Re-solve results
A2: 1 | B2: =HYPERLINK("PROBLEMS.md#x-array-basics","Array basics: print, sum, max, min, count of a target (handle empty input)") | C2: Custom | D2: Arrays | E2: Not started | L2: =IF(F2="","",F2+1) | M2: =IF(F2="","",F2+3) | N2: =IF(F2="","",F2+7) | O2: =IF(F2="","",F2+14)
A3: 2 | B3: =HYPERLINK("PROBLEMS.md#x-linear-search","Linear search, first/last occurrence, minimum/maximum with index") | C3: Custom | D3: Arrays | E3: Not started | L3: =IF(F3="","",F3+1) | M3: =IF(F3="","",F3+3) | N3: =IF(F3="","",F3+7) | O3: =IF(F3="","",F3+14)
A4: 3 | B4: =HYPERLINK("PROBLEMS.md#x-reverse","Reverse an array in place with two indexes (0, 1, odd, even lengths)") | C4: Custom | D4: Arrays | E4: Not started | L4: =IF(F4="","",F4+1) | M4: =IF(F4="","",F4+3) | N4: =IF(F4="","",F4+7) | O4: =IF(F4="","",F4+14)
A5: 4 | B5: =HYPERLINK("PROBLEMS.md#x-sorted-second","Check sorted order; second-largest DISTINCT value") | C5: Custom | D5: Arrays | E5: Not started | L5: =IF(F5="","",F5+1) | M5: =IF(F5="","",F5+3) | N5: =IF(F5="","",F5+7) | O5: =IF(F5="","",F5+14)
A6: 5 | B6: =HYPERLINK("https://leetcode.com/problems/concatenation-of-array/","Concatenation of Array (1929)") | C6: Easy | D6: Arrays | E6: Not started | L6: =IF(F6="","",F6+1) | M6: =IF(F6="","",F6+3) | N6: =IF(F6="","",F6+7) | O6: =IF(F6="","",F6+14)
A7: 5 | B7: =HYPERLINK("https://leetcode.com/problems/detect-squares/","Detect Squares (2013)") | C7: Medium | D7: Hashing | E7: Not started | L7: =IF(F7="","",F7+1) | M7: =IF(F7="","",F7+3) | N7: =IF(F7="","",F7+7) | O7: =IF(F7="","",F7+14)
A8: 6 | B8: =HYPERLINK("https://leetcode.com/problems/contains-duplicate/","Contains Duplicate (217)") | C8: Easy | D8: Hashing | E8: Not started | L8: =IF(F8="","",F8+1) | M8: =IF(F8="","",F8+3) | N8: =IF(F8="","",F8+7) | O8: =IF(F8="","",F8+14)
A9: 6 | B9: =HYPERLINK("PROBLEMS.md#x-insert-delete","Insert / delete at an index by shifting, with spare capacity") | C9: Custom | D9: Arrays | E9: Not started | L9: =IF(F9="","",F9+1) | M9: =IF(F9="","",F9+3) | N9: =IF(F9="","",F9+7) | O9: =IF(F9="","",F9+14)
A10: 8 | B10: =HYPERLINK("PROBLEMS.md#x-frequency","Frequency map of an int[] with Dictionary (TryGetValue)") | C10: Custom | D10: Hashing | E10: Not started | L10: =IF(F10="","",F10+1) | M10: =IF(F10="","",F10+3) | N10: =IF(F10="","",F10+7) | O10: =IF(F10="","",F10+14)
A11: 9 | B11: =HYPERLINK("https://leetcode.com/problems/two-sum/","Two Sum (1)") | C11: Easy | D11: Hashing | E11: Not started | L11: =IF(F11="","",F11+1) | M11: =IF(F11="","",F11+3) | N11: =IF(F11="","",F11+7) | O11: =IF(F11="","",F11+14)
A12: 10 | B12: =HYPERLINK("https://leetcode.com/problems/longest-consecutive-sequence/","Longest Consecutive Sequence (128)") | C12: Medium | D12: Hashing | E12: Not started | L12: =IF(F12="","",F12+1) | M12: =IF(F12="","",F12+3) | N12: =IF(F12="","",F12+7) | O12: =IF(F12="","",F12+14)
A13: 11 | B13: =HYPERLINK("https://leetcode.com/problems/remove-element/","Remove Element (27)") | C13: Easy | D13: Two pointers | E13: Not started | L13: =IF(F13="","",F13+1) | M13: =IF(F13="","",F13+3) | N13: =IF(F13="","",F13+7) | O13: =IF(F13="","",F13+14)
A14: 11 | B14: =HYPERLINK("https://leetcode.com/problems/move-zeroes/","Move Zeroes (283)") | C14: Easy | D14: Two pointers | E14: Not started | L14: =IF(F14="","",F14+1) | M14: =IF(F14="","",F14+3) | N14: =IF(F14="","",F14+7) | O14: =IF(F14="","",F14+14)
A15: 12 | B15: =HYPERLINK("https://leetcode.com/problems/range-sum-query-2d-immutable/","Range Sum Query 2D - Immutable (304)") | C15: Medium | D15: Prefix sum | E15: Not started | L15: =IF(F15="","",F15+1) | M15: =IF(F15="","",F15+3) | N15: =IF(F15="","",F15+7) | O15: =IF(F15="","",F15+14)
A16: 12 | B16: =HYPERLINK("https://leetcode.com/problems/find-all-numbers-disappeared-in-an-array/","Find All Numbers Disappeared in an Array (448)") | C16: Easy | D16: Arrays | E16: Not started | L16: =IF(F16="","",F16+1) | M16: =IF(F16="","",F16+3) | N16: =IF(F16="","",F16+7) | O16: =IF(F16="","",F16+14)
A17: 13 | B17: =HYPERLINK("https://leetcode.com/problems/running-sum-of-1d-array/","Running Sum of 1d Array (1480)") | C17: Easy | D17: Prefix sum | E17: Not started | L17: =IF(F17="","",F17+1) | M17: =IF(F17="","",F17+3) | N17: =IF(F17="","",F17+7) | O17: =IF(F17="","",F17+14)
A18: 13 | B18: =HYPERLINK("https://leetcode.com/problems/remove-duplicates-from-sorted-array/","Remove Duplicates from Sorted Array (26)") | C18: Easy | D18: Two pointers | E18: Not started | L18: =IF(F18="","",F18+1) | M18: =IF(F18="","",F18+3) | N18: =IF(F18="","",F18+7) | O18: =IF(F18="","",F18+14)
A19: 13 | B19: =HYPERLINK("https://leetcode.com/problems/range-sum-query-immutable/","Range Sum Query - Immutable (303)") | C19: Easy | D19: Prefix sum | E19: Not started | L19: =IF(F19="","",F19+1) | M19: =IF(F19="","",F19+3) | N19: =IF(F19="","",F19+7) | O19: =IF(F19="","",F19+14)
A20: 13 | B20: =HYPERLINK("https://leetcode.com/problems/plus-one/","Plus One (66)") | C20: Easy | D20: Arrays | E20: Not started | L20: =IF(F20="","",F20+1) | M20: =IF(F20="","",F20+3) | N20: =IF(F20="","",F20+7) | O20: =IF(F20="","",F20+14)
A21: 13 | B21: =HYPERLINK("https://leetcode.com/problems/merge-sorted-array/","Merge Sorted Array (88)") | C21: Easy | D21: Two pointers | E21: Not started | L21: =IF(F21="","",F21+1) | M21: =IF(F21="","",F21+3) | N21: =IF(F21="","",F21+7) | O21: =IF(F21="","",F21+14)
A22: 15 | B22: =HYPERLINK("https://leetcode.com/problems/valid-anagram/","Valid Anagram (242)") | C22: Easy | D22: Strings | E22: Not started | L22: =IF(F22="","",F22+1) | M22: =IF(F22="","",F22+3) | N22: =IF(F22="","",F22+7) | O22: =IF(F22="","",F22+14)
A23: 15 | B23: =HYPERLINK("https://leetcode.com/problems/ransom-note/","Ransom Note (383)") | C23: Easy | D23: Strings | E23: Not started | L23: =IF(F23="","",F23+1) | M23: =IF(F23="","",F23+3) | N23: =IF(F23="","",F23+7) | O23: =IF(F23="","",F23+14)
A24: 16 | B24: =HYPERLINK("https://leetcode.com/problems/valid-palindrome/","Valid Palindrome (125)") | C24: Easy | D24: Two pointers | E24: Not started | L24: =IF(F24="","",F24+1) | M24: =IF(F24="","",F24+3) | N24: =IF(F24="","",F24+7) | O24: =IF(F24="","",F24+14)
A25: 16 | B25: =HYPERLINK("https://leetcode.com/problems/valid-palindrome-ii/","Valid Palindrome II (680)") | C25: Easy | D25: Two pointers | E25: Not started | L25: =IF(F25="","",F25+1) | M25: =IF(F25="","",F25+3) | N25: =IF(F25="","",F25+7) | O25: =IF(F25="","",F25+14)
A26: 17 | B26: =HYPERLINK("https://leetcode.com/problems/two-sum-ii-input-array-is-sorted/","Two Sum II - Input Array Is Sorted (167)") | C26: Medium | D26: Two pointers | E26: Not started | L26: =IF(F26="","",F26+1) | M26: =IF(F26="","",F26+3) | N26: =IF(F26="","",F26+7) | O26: =IF(F26="","",F26+14)
A27: 17 | B27: =HYPERLINK("https://leetcode.com/problems/squares-of-a-sorted-array/","Squares of a Sorted Array (977)") | C27: Easy | D27: Two pointers | E27: Not started | L27: =IF(F27="","",F27+1) | M27: =IF(F27="","",F27+3) | N27: =IF(F27="","",F27+7) | O27: =IF(F27="","",F27+14)
A28: 18 | B28: =HYPERLINK("https://leetcode.com/problems/longest-common-prefix/","Longest Common Prefix (14)") | C28: Easy | D28: Strings | E28: Not started | L28: =IF(F28="","",F28+1) | M28: =IF(F28="","",F28+3) | N28: =IF(F28="","",F28+7) | O28: =IF(F28="","",F28+14)
A29: 18 | B29: =HYPERLINK("https://leetcode.com/problems/maximum-average-subarray-i/","Maximum Average Subarray I (643)") | C29: Easy | D29: Sliding window | E29: Not started | L29: =IF(F29="","",F29+1) | M29: =IF(F29="","",F29+3) | N29: =IF(F29="","",F29+7) | O29: =IF(F29="","",F29+14)
A30: 19 | B30: =HYPERLINK("https://leetcode.com/problems/encode-and-decode-strings/","Encode and Decode Strings (271)") | C30: Medium | D30: Strings | E30: Not started | L30: =IF(F30="","",F30+1) | M30: =IF(F30="","",F30+3) | N30: =IF(F30="","",F30+7) | O30: =IF(F30="","",F30+14)
A31: 19 | B31: =HYPERLINK("https://leetcode.com/problems/reverse-string/","Reverse String (344)") | C31: Easy | D31: Two pointers | E31: Not started | L31: =IF(F31="","",F31+1) | M31: =IF(F31="","",F31+3) | N31: =IF(F31="","",F31+7) | O31: =IF(F31="","",F31+14)
A32: 20 | B32: =HYPERLINK("https://leetcode.com/problems/3sum/","3Sum (15)") | C32: Medium | D32: Two pointers | E32: Not started | L32: =IF(F32="","",F32+1) | M32: =IF(F32="","",F32+3) | N32: =IF(F32="","",F32+7) | O32: =IF(F32="","",F32+14)
A33: 20 | B33: =HYPERLINK("https://leetcode.com/problems/isomorphic-strings/","Isomorphic Strings (205)") | C33: Easy | D33: Strings | E33: Not started | L33: =IF(F33="","",F33+1) | M33: =IF(F33="","",F33+3) | N33: =IF(F33="","",F33+7) | O33: =IF(F33="","",F33+14)
A34: 20 | B34: =HYPERLINK("https://leetcode.com/problems/word-pattern/","Word Pattern (290)") | C34: Easy | D34: Strings | E34: Not started | L34: =IF(F34="","",F34+1) | M34: =IF(F34="","",F34+3) | N34: =IF(F34="","",F34+7) | O34: =IF(F34="","",F34+14)
A35: 20 | B35: =HYPERLINK("https://leetcode.com/problems/first-unique-character-in-a-string/","First Unique Character in a String (387)") | C35: Easy | D35: Strings | E35: Not started | L35: =IF(F35="","",F35+1) | M35: =IF(F35="","",F35+3) | N35: =IF(F35="","",F35+7) | O35: =IF(F35="","",F35+14)
A36: 22 | B36: =HYPERLINK("https://leetcode.com/problems/longest-substring-without-repeating-characters/","Longest Substring Without Repeating Characters (3)") | C36: Medium | D36: Sliding window | E36: Not started | L36: =IF(F36="","",F36+1) | M36: =IF(F36="","",F36+3) | N36: =IF(F36="","",F36+7) | O36: =IF(F36="","",F36+14)
A37: 23 | B37: =HYPERLINK("https://leetcode.com/problems/max-consecutive-ones-iii/","Max Consecutive Ones III (1004)") | C37: Medium | D37: Sliding window | E37: Not started | L37: =IF(F37="","",F37+1) | M37: =IF(F37="","",F37+3) | N37: =IF(F37="","",F37+7) | O37: =IF(F37="","",F37+14)
A38: 23 | B38: =HYPERLINK("https://leetcode.com/problems/minimum-size-subarray-sum/","Minimum Size Subarray Sum (209)") | C38: Medium | D38: Sliding window | E38: Not started | L38: =IF(F38="","",F38+1) | M38: =IF(F38="","",F38+3) | N38: =IF(F38="","",F38+7) | O38: =IF(F38="","",F38+14)
A39: 24 | B39: =HYPERLINK("https://leetcode.com/problems/subarray-sum-equals-k/","Subarray Sum Equals K (560)") | C39: Medium | D39: Prefix sum | E39: Not started | L39: =IF(F39="","",F39+1) | M39: =IF(F39="","",F39+3) | N39: =IF(F39="","",F39+7) | O39: =IF(F39="","",F39+14)
A40: 25 | B40: =HYPERLINK("https://leetcode.com/problems/best-time-to-buy-and-sell-stock/","Best Time to Buy and Sell Stock (121)") | C40: Easy | D40: Arrays | E40: Not started | L40: =IF(F40="","",F40+1) | M40: =IF(F40="","",F40+3) | N40: =IF(F40="","",F40+7) | O40: =IF(F40="","",F40+14)
A41: 25 | B41: =HYPERLINK("https://leetcode.com/problems/maximum-subarray/","Maximum Subarray (53)") | C41: Medium | D41: Arrays | E41: Not started | L41: =IF(F41="","",F41+1) | M41: =IF(F41="","",F41+3) | N41: =IF(F41="","",F41+7) | O41: =IF(F41="","",F41+14)
A42: 26 | B42: =HYPERLINK("https://leetcode.com/problems/contains-duplicate-ii/","Contains Duplicate II (219)") | C42: Easy | D42: Hashing | E42: Not started | L42: =IF(F42="","",F42+1) | M42: =IF(F42="","",F42+3) | N42: =IF(F42="","",F42+7) | O42: =IF(F42="","",F42+14)
A43: 27 | B43: =HYPERLINK("https://leetcode.com/problems/product-of-array-except-self/","Product of Array Except Self (238)") | C43: Medium | D43: Prefix sum | E43: Not started | L43: =IF(F43="","",F43+1) | M43: =IF(F43="","",F43+3) | N43: =IF(F43="","",F43+7) | O43: =IF(F43="","",F43+14)
A44: 27 | B44: =HYPERLINK("https://leetcode.com/problems/longest-repeating-character-replacement/","Longest Repeating Character Replacement (424)") | C44: Medium | D44: Sliding window | E44: Not started | L44: =IF(F44="","",F44+1) | M44: =IF(F44="","",F44+3) | N44: =IF(F44="","",F44+7) | O44: =IF(F44="","",F44+14)
A45: 27 | B45: =HYPERLINK("https://leetcode.com/problems/group-anagrams/","Group Anagrams (49)") | C45: Medium | D45: Hashing | E45: Not started | L45: =IF(F45="","",F45+1) | M45: =IF(F45="","",F45+3) | N45: =IF(F45="","",F45+7) | O45: =IF(F45="","",F45+14)
A46: 27 | B46: =HYPERLINK("https://leetcode.com/problems/permutation-in-string/","Permutation in String (567)") | C46: Medium | D46: Sliding window | E46: Not started | L46: =IF(F46="","",F46+1) | M46: =IF(F46="","",F46+3) | N46: =IF(F46="","",F46+7) | O46: =IF(F46="","",F46+14)
A47: 29 | B47: =HYPERLINK("https://leetcode.com/problems/search-insert-position/","Search Insert Position (35)") | C47: Easy | D47: Binary search | E47: Not started | L47: =IF(F47="","",F47+1) | M47: =IF(F47="","",F47+3) | N47: =IF(F47="","",F47+7) | O47: =IF(F47="","",F47+14)
A48: 29 | B48: =HYPERLINK("https://leetcode.com/problems/binary-search/","Binary Search (704)") | C48: Easy | D48: Binary search | E48: Not started | L48: =IF(F48="","",F48+1) | M48: =IF(F48="","",F48+3) | N48: =IF(F48="","",F48+7) | O48: =IF(F48="","",F48+14)
A49: 30 | B49: =HYPERLINK("https://leetcode.com/problems/first-bad-version/","First Bad Version (278)") | C49: Easy | D49: Binary search | E49: Not started | L49: =IF(F49="","",F49+1) | M49: =IF(F49="","",F49+3) | N49: =IF(F49="","",F49+7) | O49: =IF(F49="","",F49+14)
A50: 30 | B50: =HYPERLINK("https://leetcode.com/problems/find-first-and-last-position-of-element-in-sorted-array/","Find First and Last Position of Element in Sorted Array (34)") | C50: Medium | D50: Binary search | E50: Not started | L50: =IF(F50="","",F50+1) | M50: =IF(F50="","",F50+3) | N50: =IF(F50="","",F50+7) | O50: =IF(F50="","",F50+14)
A51: 31 | B51: =HYPERLINK("https://leetcode.com/problems/find-minimum-in-rotated-sorted-array/","Find Minimum in Rotated Sorted Array (153)") | C51: Medium | D51: Binary search | E51: Not started | L51: =IF(F51="","",F51+1) | M51: =IF(F51="","",F51+3) | N51: =IF(F51="","",F51+7) | O51: =IF(F51="","",F51+14)
A52: 31 | B52: =HYPERLINK("https://leetcode.com/problems/search-in-rotated-sorted-array/","Search in Rotated Sorted Array (33)") | C52: Medium | D52: Binary search | E52: Not started | L52: =IF(F52="","",F52+1) | M52: =IF(F52="","",F52+3) | N52: =IF(F52="","",F52+7) | O52: =IF(F52="","",F52+14)
A53: 32 | B53: =HYPERLINK("https://leetcode.com/problems/capacity-to-ship-packages-within-d-days/","Capacity To Ship Packages Within D Days (1011)") | C53: Medium | D53: Binary search on answer | E53: Not started | L53: =IF(F53="","",F53+1) | M53: =IF(F53="","",F53+3) | N53: =IF(F53="","",F53+7) | O53: =IF(F53="","",F53+14)
A54: 32 | B54: =HYPERLINK("https://leetcode.com/problems/koko-eating-bananas/","Koko Eating Bananas (875)") | C54: Medium | D54: Binary search on answer | E54: Not started | L54: =IF(F54="","",F54+1) | M54: =IF(F54="","",F54+3) | N54: =IF(F54="","",F54+7) | O54: =IF(F54="","",F54+14)
A55: 33 | B55: =HYPERLINK("https://leetcode.com/problems/sqrtx/","Sqrt(x) (69)") | C55: Easy | D55: Binary search | E55: Not started | L55: =IF(F55="","",F55+1) | M55: =IF(F55="","",F55+3) | N55: =IF(F55="","",F55+7) | O55: =IF(F55="","",F55+14)
A56: 33 | B56: =HYPERLINK("https://leetcode.com/problems/search-a-2d-matrix/","Search a 2D Matrix (74)") | C56: Medium | D56: Binary search | E56: Not started | L56: =IF(F56="","",F56+1) | M56: =IF(F56="","",F56+3) | N56: =IF(F56="","",F56+7) | O56: =IF(F56="","",F56+14)
A57: 34 | B57: =HYPERLINK("https://leetcode.com/problems/sort-colors/","Sort Colors (75)") | C57: Medium | D57: Two pointers | E57: Not started | L57: =IF(F57="","",F57+1) | M57: =IF(F57="","",F57+3) | N57: =IF(F57="","",F57+7) | O57: =IF(F57="","",F57+14)
A58: 34 | B58: =HYPERLINK("https://leetcode.com/problems/sort-an-array/","Sort an Array (912)") | C58: Medium | D58: Sorting | E58: Not started | L58: =IF(F58="","",F58+1) | M58: =IF(F58="","",F58+3) | N58: =IF(F58="","",F58+7) | O58: =IF(F58="","",F58+14)
A59: 34 | B59: =HYPERLINK("PROBLEMS.md#x-merge-sort","Implement merge sort (stable, O(n log n), O(n) extra)") | C59: Custom | D59: Sorting | E59: Not started | L59: =IF(F59="","",F59+1) | M59: =IF(F59="","",F59+3) | N59: =IF(F59="","",F59+7) | O59: =IF(F59="","",F59+14)
A60: 34 | B60: =HYPERLINK("PROBLEMS.md#x-quick-sort","Implement quicksort partition (Lomuto and Hoare) and quickselect") | C60: Custom | D60: Sorting | E60: Not started | L60: =IF(F60="","",F60+1) | M60: =IF(F60="","",F60+3) | N60: =IF(F60="","",F60+7) | O60: =IF(F60="","",F60+14)
A61: 35 | B61: =HYPERLINK("PROBLEMS.md#x-simple-sorts","Bubble, selection, insertion sort — trace and state costs") | C61: Custom | D61: Sorting | E61: Not started | L61: =IF(F61="","",F61+1) | M61: =IF(F61="","",F61+3) | N61: =IF(F61="","",F61+7) | O61: =IF(F61="","",F61+14)
A62: 36 | B62: =HYPERLINK("https://leetcode.com/problems/reverse-linked-list/","Reverse Linked List (206)") | C62: Easy | D62: Linked lists | E62: Not started | L62: =IF(F62="","",F62+1) | M62: =IF(F62="","",F62+3) | N62: =IF(F62="","",F62+7) | O62: =IF(F62="","",F62+14)
A63: 36 | B63: =HYPERLINK("https://leetcode.com/problems/middle-of-the-linked-list/","Middle of the Linked List (876)") | C63: Easy | D63: Fast & slow | E63: Not started | L63: =IF(F63="","",F63+1) | M63: =IF(F63="","",F63+3) | N63: =IF(F63="","",F63+7) | O63: =IF(F63="","",F63+14)
A64: 37 | B64: =HYPERLINK("https://leetcode.com/problems/remove-nth-node-from-end-of-list/","Remove Nth Node From End of List (19)") | C64: Medium | D64: Linked lists | E64: Not started | L64: =IF(F64="","",F64+1) | M64: =IF(F64="","",F64+3) | N64: =IF(F64="","",F64+7) | O64: =IF(F64="","",F64+14)
A65: 37 | B65: =HYPERLINK("https://leetcode.com/problems/merge-two-sorted-lists/","Merge Two Sorted Lists (21)") | C65: Easy | D65: Linked lists | E65: Not started | L65: =IF(F65="","",F65+1) | M65: =IF(F65="","",F65+3) | N65: =IF(F65="","",F65+7) | O65: =IF(F65="","",F65+14)
A66: 38 | B66: =HYPERLINK("https://leetcode.com/problems/linked-list-cycle/","Linked List Cycle (141)") | C66: Easy | D66: Fast & slow | E66: Not started | L66: =IF(F66="","",F66+1) | M66: =IF(F66="","",F66+3) | N66: =IF(F66="","",F66+7) | O66: =IF(F66="","",F66+14)
A67: 38 | B67: =HYPERLINK("https://leetcode.com/problems/palindrome-linked-list/","Palindrome Linked List (234)") | C67: Easy | D67: Linked lists | E67: Not started | L67: =IF(F67="","",F67+1) | M67: =IF(F67="","",F67+3) | N67: =IF(F67="","",F67+7) | O67: =IF(F67="","",F67+14)
A68: 39 | B68: =HYPERLINK("https://leetcode.com/problems/valid-parentheses/","Valid Parentheses (20)") | C68: Easy | D68: Stack & Queue | E68: Not started | L68: =IF(F68="","",F68+1) | M68: =IF(F68="","",F68+3) | N68: =IF(F68="","",F68+7) | O68: =IF(F68="","",F68+14)
A69: 39 | B69: =HYPERLINK("https://leetcode.com/problems/implement-queue-using-stacks/","Implement Queue using Stacks (232)") | C69: Easy | D69: Stack & Queue | E69: Not started | L69: =IF(F69="","",F69+1) | M69: =IF(F69="","",F69+3) | N69: =IF(F69="","",F69+7) | O69: =IF(F69="","",F69+14)
A70: 40 | B70: =HYPERLINK("https://leetcode.com/problems/intersection-of-two-linked-lists/","Intersection of Two Linked Lists (160)") | C70: Easy | D70: Linked lists | E70: Not started | L70: =IF(F70="","",F70+1) | M70: =IF(F70="","",F70+3) | N70: =IF(F70="","",F70+7) | O70: =IF(F70="","",F70+14)
A71: 40 | B71: =HYPERLINK("https://leetcode.com/problems/implement-stack-using-queues/","Implement Stack using Queues (225)") | C71: Easy | D71: Stack & Queue | E71: Not started | L71: =IF(F71="","",F71+1) | M71: =IF(F71="","",F71+3) | N71: =IF(F71="","",F71+7) | O71: =IF(F71="","",F71+14)
A72: 40 | B72: =HYPERLINK("https://leetcode.com/problems/design-circular-queue/","Design Circular Queue (622)") | C72: Medium | D72: Stack & Queue | E72: Not started | L72: =IF(F72="","",F72+1) | M72: =IF(F72="","",F72+3) | N72: =IF(F72="","",F72+7) | O72: =IF(F72="","",F72+14)
A73: 40 | B73: =HYPERLINK("https://leetcode.com/problems/reverse-linked-list-ii/","Reverse Linked List II (92)") | C73: Medium | D73: Linked lists | E73: Not started | L73: =IF(F73="","",F73+1) | M73: =IF(F73="","",F73+3) | N73: =IF(F73="","",F73+7) | O73: =IF(F73="","",F73+14)
A74: 41 | B74: =HYPERLINK("https://leetcode.com/problems/reorder-list/","Reorder List (143)") | C74: Medium | D74: Linked lists | E74: Not started | L74: =IF(F74="","",F74+1) | M74: =IF(F74="","",F74+3) | N74: =IF(F74="","",F74+7) | O74: =IF(F74="","",F74+14)
A75: 41 | B75: =HYPERLINK("https://leetcode.com/problems/evaluate-reverse-polish-notation/","Evaluate Reverse Polish Notation (150)") | C75: Medium | D75: Stack & Queue | E75: Not started | L75: =IF(F75="","",F75+1) | M75: =IF(F75="","",F75+3) | N75: =IF(F75="","",F75+7) | O75: =IF(F75="","",F75+14)
A76: 41 | B76: =HYPERLINK("https://leetcode.com/problems/min-stack/","Min Stack (155)") | C76: Medium | D76: Stack & Queue | E76: Not started | L76: =IF(F76="","",F76+1) | M76: =IF(F76="","",F76+3) | N76: =IF(F76="","",F76+7) | O76: =IF(F76="","",F76+14)
A77: 41 | B77: =HYPERLINK("https://leetcode.com/problems/add-two-numbers/","Add Two Numbers (2)") | C77: Medium | D77: Linked lists | E77: Not started | L77: =IF(F77="","",F77+1) | M77: =IF(F77="","",F77+3) | N77: =IF(F77="","",F77+7) | O77: =IF(F77="","",F77+14)
A78: 43 | B78: =HYPERLINK("https://leetcode.com/problems/fibonacci-number/","Fibonacci Number (509)") | C78: Easy | D78: Recursion | E78: Not started | L78: =IF(F78="","",F78+1) | M78: =IF(F78="","",F78+3) | N78: =IF(F78="","",F78+7) | O78: =IF(F78="","",F78+14)
A79: 43 | B79: =HYPERLINK("PROBLEMS.md#x-fib-three-ways","Fibonacci three ways: naive recursion, memo, iterative — compare cost") | C79: Custom | D79: Recursion | E79: Not started | L79: =IF(F79="","",F79+1) | M79: =IF(F79="","",F79+3) | N79: =IF(F79="","",F79+7) | O79: =IF(F79="","",F79+14)
A80: 43 | B80: =HYPERLINK("PROBLEMS.md#x-recursion-basics","Recursive sum, factorial, power, reverse a string — draw the call stack") | C80: Custom | D80: Recursion | E80: Not started | L80: =IF(F80="","",F80+1) | M80: =IF(F80="","",F80+3) | N80: =IF(F80="","",F80+7) | O80: =IF(F80="","",F80+14)
A81: 44 | B81: =HYPERLINK("https://leetcode.com/problems/powx-n/","Pow(x, n) (50)") | C81: Medium | D81: Recursion | E81: Not started | L81: =IF(F81="","",F81+1) | M81: =IF(F81="","",F81+3) | N81: =IF(F81="","",F81+7) | O81: =IF(F81="","",F81+14)
A82: 44 | B82: =HYPERLINK("https://leetcode.com/problems/subsets/","Subsets (78)") | C82: Medium | D82: Backtracking | E82: Not started | L82: =IF(F82="","",F82+1) | M82: =IF(F82="","",F82+3) | N82: =IF(F82="","",F82+7) | O82: =IF(F82="","",F82+14)
A83: 45 | B83: =HYPERLINK("https://leetcode.com/problems/letter-combinations-of-a-phone-number/","Letter Combinations of a Phone Number (17)") | C83: Medium | D83: Backtracking | E83: Not started | L83: =IF(F83="","",F83+1) | M83: =IF(F83="","",F83+3) | N83: =IF(F83="","",F83+7) | O83: =IF(F83="","",F83+14)
A84: 45 | B84: =HYPERLINK("https://leetcode.com/problems/permutations/","Permutations (46)") | C84: Medium | D84: Backtracking | E84: Not started | L84: =IF(F84="","",F84+1) | M84: =IF(F84="","",F84+3) | N84: =IF(F84="","",F84+7) | O84: =IF(F84="","",F84+14)
A85: 46 | B85: =HYPERLINK("https://leetcode.com/problems/generate-parentheses/","Generate Parentheses (22)") | C85: Medium | D85: Backtracking | E85: Not started | L85: =IF(F85="","",F85+1) | M85: =IF(F85="","",F85+3) | N85: =IF(F85="","",F85+7) | O85: =IF(F85="","",F85+14)
A86: 46 | B86: =HYPERLINK("https://leetcode.com/problems/combination-sum/","Combination Sum (39)") | C86: Medium | D86: Backtracking | E86: Not started | L86: =IF(F86="","",F86+1) | M86: =IF(F86="","",F86+3) | N86: =IF(F86="","",F86+7) | O86: =IF(F86="","",F86+14)
A87: 47 | B87: =HYPERLINK("https://leetcode.com/problems/combination-sum-iii/","Combination Sum III (216)") | C87: Medium | D87: Backtracking | E87: Not started | L87: =IF(F87="","",F87+1) | M87: =IF(F87="","",F87+3) | N87: =IF(F87="","",F87+7) | O87: =IF(F87="","",F87+14)
A88: 47 | B88: =HYPERLINK("https://leetcode.com/problems/combination-sum-ii/","Combination Sum II (40)") | C88: Medium | D88: Backtracking | E88: Not started | L88: =IF(F88="","",F88+1) | M88: =IF(F88="","",F88+3) | N88: =IF(F88="","",F88+7) | O88: =IF(F88="","",F88+14)
A89: 48 | B89: =HYPERLINK("https://leetcode.com/problems/palindrome-partitioning/","Palindrome Partitioning (131)") | C89: Medium | D89: Backtracking | E89: Not started | L89: =IF(F89="","",F89+1) | M89: =IF(F89="","",F89+3) | N89: =IF(F89="","",F89+7) | O89: =IF(F89="","",F89+14)
A90: 48 | B90: =HYPERLINK("https://leetcode.com/problems/permutations-ii/","Permutations II (47)") | C90: Medium | D90: Backtracking | E90: Not started | L90: =IF(F90="","",F90+1) | M90: =IF(F90="","",F90+3) | N90: =IF(F90="","",F90+7) | O90: =IF(F90="","",F90+14)
A91: 48 | B91: =HYPERLINK("https://leetcode.com/problems/word-search/","Word Search (79)") | C91: Medium | D91: Backtracking | E91: Not started | L91: =IF(F91="","",F91+1) | M91: =IF(F91="","",F91+3) | N91: =IF(F91="","",F91+7) | O91: =IF(F91="","",F91+14)
A92: 48 | B92: =HYPERLINK("https://leetcode.com/problems/subsets-ii/","Subsets II (90)") | C92: Medium | D92: Backtracking | E92: Not started | L92: =IF(F92="","",F92+1) | M92: =IF(F92="","",F92+3) | N92: =IF(F92="","",F92+7) | O92: =IF(F92="","",F92+14)
A93: 49 | B93: =HYPERLINK("https://leetcode.com/problems/n-queens/","N-Queens (51)") | C93: Hard | D93: Backtracking | E93: Not started | L93: =IF(F93="","",F93+1) | M93: =IF(F93="","",F93+3) | N93: =IF(F93="","",F93+7) | O93: =IF(F93="","",F93+14)
A94: 50 | B94: =HYPERLINK("https://leetcode.com/problems/same-tree/","Same Tree (100)") | C94: Easy | D94: Trees | E94: Not started | L94: =IF(F94="","",F94+1) | M94: =IF(F94="","",F94+3) | N94: =IF(F94="","",F94+7) | O94: =IF(F94="","",F94+14)
A95: 50 | B95: =HYPERLINK("https://leetcode.com/problems/maximum-depth-of-binary-tree/","Maximum Depth of Binary Tree (104)") | C95: Easy | D95: Trees | E95: Not started | L95: =IF(F95="","",F95+1) | M95: =IF(F95="","",F95+3) | N95: =IF(F95="","",F95+7) | O95: =IF(F95="","",F95+14)
A96: 50 | B96: =HYPERLINK("https://leetcode.com/problems/invert-binary-tree/","Invert Binary Tree (226)") | C96: Easy | D96: Trees | E96: Not started | L96: =IF(F96="","",F96+1) | M96: =IF(F96="","",F96+3) | N96: =IF(F96="","",F96+7) | O96: =IF(F96="","",F96+14)
A97: 51 | B97: =HYPERLINK("https://leetcode.com/problems/binary-tree-level-order-traversal/","Binary Tree Level Order Traversal (102)") | C97: Medium | D97: Trees | E97: Not started | L97: =IF(F97="","",F97+1) | M97: =IF(F97="","",F97+3) | N97: =IF(F97="","",F97+7) | O97: =IF(F97="","",F97+14)
A98: 51 | B98: =HYPERLINK("https://leetcode.com/problems/binary-tree-right-side-view/","Binary Tree Right Side View (199)") | C98: Medium | D98: Trees | E98: Not started | L98: =IF(F98="","",F98+1) | M98: =IF(F98="","",F98+3) | N98: =IF(F98="","",F98+7) | O98: =IF(F98="","",F98+14)
A99: 52 | B99: =HYPERLINK("https://leetcode.com/problems/kth-smallest-element-in-a-bst/","Kth Smallest Element in a BST (230)") | C99: Medium | D99: BST | E99: Not started | L99: =IF(F99="","",F99+1) | M99: =IF(F99="","",F99+3) | N99: =IF(F99="","",F99+7) | O99: =IF(F99="","",F99+14)
A100: 52 | B100: =HYPERLINK("https://leetcode.com/problems/validate-binary-search-tree/","Validate Binary Search Tree (98)") | C100: Medium | D100: BST | E100: Not started | L100: =IF(F100="","",F100+1) | M100: =IF(F100="","",F100+3) | N100: =IF(F100="","",F100+7) | O100: =IF(F100="","",F100+14)
...

Sheet REVIEW
A1: Planned day | B1: Concept (explain aloud) | C1: Learned on | D1: D+1 | E1: D+3 | F1: D+7 | G1: D+14 | H1: D+30 | I1: Last result
A2: 1 | B2: Why is reading a[i] O(1) but finding a value O(n)? | D2: =IF(C2="","",C2+1) | E2: =IF(C2="","",C2+3) | F2: =IF(C2="","",C2+7) | G2: =IF(C2="","",C2+14) | H2: =IF(C2="","",C2+30)
A3: 2 | B3: What is overflow and when should a sum use long? | D3: =IF(C3="","",C3+1) | E3: =IF(C3="","",C3+3) | F3: =IF(C3="","",C3+7) | G3: =IF(C3="","",C3+14) | H3: =IF(C3="","",C3+30)
A4: 3 | B4: What does a variable of a value type hold, and what does a reference-type variable hold? | D4: =IF(C4="","",C4+1) | E4: =IF(C4="","",C4+3) | F4: =IF(C4="","",C4+7) | G4: =IF(C4="","",C4+14) | H4: =IF(C4="","",C4+30)
A5: 4 | B5: Where does a struct live — the stack or the heap? (It depends on where it is declared.) | D5: =IF(C5="","",C5+1) | E5: =IF(C5="","",C5+3) | F5: =IF(C5="","",C5+7) | G5: =IF(C5="","",C5+14) | H5: =IF(C5="","",C5+30)
A6: 8 | B6: What is boxing, what does it cost, and name three places it happens by accident. | D6: =IF(C6="","",C6+1) | E6: =IF(C6="","",C6+3) | F6: =IF(C6="","",C6+7) | G6: =IF(C6="","",C6+14) | H6: =IF(C6="","",C6+30)
A7: 9 | B7: State the Equals/GetHashCode contract and what breaks without it. | D7: =IF(C7="","",C7+1) | E7: =IF(C7="","",C7+3) | F7: =IF(C7="","",C7+7) | G7: =IF(C7="","",C7+14) | H7: =IF(C7="","",C7+30)
A8: 10 | B8: Why is Dictionary lookup O(1) on average, and what makes it O(n)? | D8: =IF(C8="","",C8+1) | E8: =IF(C8="","",C8+3) | F8: =IF(C8="","",C8+7) | G8: =IF(C8="","",C8+14) | H8: =IF(C8="","",C8+30)
A9: 11 | B9: Explain ref, out and in in one sentence each. | D9: =IF(C9="","",C9+1) | E9: =IF(C9="","",C9+3) | F9: =IF(C9="","",C9+7) | G9: =IF(C9="","",C9+14) | H9: =IF(C9="","",C9+30)
A10: 15 | B10: Why is string concatenation in a loop O(n²)? | D10: =IF(C10="","",C10+1) | E10: =IF(C10="","",C10+3) | F10: =IF(C10="","",C10+7) | G10: =IF(C10="","",C10+14) | H10: =IF(C10="","",C10+30)
A11: 16 | B11: What is the job of a constructor? | D11: =IF(C11="","",C11+1) | E11: =IF(C11="","",C11+3) | F11: =IF(C11="","",C11+7) | G11: =IF(C11="","",C11+14) | H11: =IF(C11="","",C11+30)
A12: 17 | B12: Interface or abstract class — how do you decide? | D12: =IF(C12="","",C12+1) | E12: =IF(C12="","",C12+3) | F12: =IF(C12="","",C12+7) | G12: =IF(C12="","",C12+14) | H12: =IF(C12="","",C12+30)
A13: 18 | B13: Why composition over inheritance? | D13: =IF(C13="","",C13+1) | E13: =IF(C13="","",C13+3) | F13: =IF(C13="","",C13+7) | G13: =IF(C13="","",C13+14) | H13: =IF(C13="","",C13+30)
... A129: 221 | B129: What did these eight months change in how you engineer? | D129: =IF(C129="","",C129+1) | E129: =IF(C129="","",C129+3) | F129: =IF(C129="","",C129+7) | G129: =IF(C129="","",C129+14) | H129: =IF(C129="","",C129+30)

Sheet WEAK
A1: Item | B1: Added on | C1: Where it came from | D1: Try 1 | E1: Try 2 | F1: Cleared on | G1: Note

Sheet DESIGNS
A1: ID | B1: Type | C1: Design | D1: Planned day(s) | E1: Done on | F1: Minutes | G1: Score /20 | H1: What I missed | I1: Redo on
A2: url-shortener | B2: HLD | C2: =HYPERLINK("DESIGNS.md#hld-url-shortener","URL shortener (TinyURL)") | D2: 20, 27, 34, 55, 202
A3: pastebin | B3: HLD | C3: =HYPERLINK("DESIGNS.md#hld-pastebin","Pastebin") | D3: 117
A4: rate-limiter | B4: HLD | C4: =HYPERLINK("DESIGNS.md#hld-rate-limiter","Distributed rate limiter") | D4: 69, 202
A5: notification | B5: HLD | C5: =HYPERLINK("DESIGNS.md#hld-notification","Notification service (email/SMS/push)") | D5: 83, 146, 202
A6: job-platform | B6: HLD | C6: =HYPERLINK("DESIGNS.md#hld-job-platform","Distributed job scheduler / task queue (your project)") | D6: 76, 167, 216
A7: dropbox | B7: HLD | C7: =HYPERLINK("DESIGNS.md#hld-dropbox","File storage and sync (Dropbox / Google Drive)") | D7: 195
A8: news-feed | B8: HLD | C8: =HYPERLINK("DESIGNS.md#hld-news-feed","News feed (Facebook / Twitter timeline)") | D8: 125, 209
A9: ecommerce | B9: HLD | C9: =HYPERLINK("DESIGNS.md#hld-ecommerce","E-commerce checkout, orders and inventory (Amazon)") | D9: 139
A10: payment | B10: HLD | C10: =HYPERLINK("DESIGNS.md#hld-payment","Payment system / wallet (PhonePe)") | D10: 139, 216
A11: chat | B11: HLD | C11: =HYPERLINK("DESIGNS.md#hld-chat","Chat and messaging (WhatsApp / Slack)") | D11: 118, 209
A12: web-crawler | B12: HLD | C12: =HYPERLINK("DESIGNS.md#hld-web-crawler","Web crawler") | D12: 143
A13: youtube | B13: HLD | C13: =HYPERLINK("DESIGNS.md#hld-youtube","Video upload and streaming (YouTube)") | D13: 150, 199
A14: typeahead | B14: HLD | C14: =HYPERLINK("DESIGNS.md#hld-typeahead","Search autocomplete / typeahead") | D14: 150, 199
A15: google-docs | B15: HLD | C15: =HYPERLINK("DESIGNS.md#hld-google-docs","Collaborative editor (Google Docs)") | D15: 164
A16: distributed-cache | B16: HLD | C16: =HYPERLINK("DESIGNS.md#hld-distributed-cache","Distributed cache (Redis-like)") | D16: 165
A17: ad-click-aggregation | B17: HLD | C17: =HYPERLINK("DESIGNS.md#hld-ad-click-aggregation","Ad-click aggregation (stream processing)") | D17: 174
A18: metrics-monitoring | B18: HLD | C18: =HYPERLINK("DESIGNS.md#hld-metrics-monitoring","Metrics and monitoring system") | D18: 181
A19: proximity | B19: HLD | C19: =HYPERLINK("DESIGNS.md#hld-proximity","Proximity / nearby search (Yelp, Google Maps nearby)") | D19: 188, 199
A20: object-storage | B20: HLD | C20: =HYPERLINK("DESIGNS.md#hld-object-storage","Object storage (S3-like)") | D20: 195
A21: uber | B21: HLD | C21: =HYPERLINK("DESIGNS.md#hld-uber","Ride sharing and matching (Uber)") | D21: 188
A22: hotel-booking | B22: HLD | C22: =HYPERLINK("DESIGNS.md#hld-hotel-booking","Hotel booking (Booking.com)") | D22: 132, 216
A23: ticket-booking | B23: HLD | C23: =HYPERLINK("DESIGNS.md#hld-ticket-booking","Movie / event ticket booking (BookMyShow)") | D23: 132
A24: flight-booking | B24: HLD | C24: =HYPERLINK("DESIGNS.md#hld-flight-booking","Flight booking") | D24: 119
A25: restaurant-reservation | B25: HLD | C25: =HYPERLINK("DESIGNS.md#hld-restaurant-reservation","Restaurant reservation") | D25: 124
A26: food-delivery | B26: HLD | C26: =HYPERLINK("DESIGNS.md#hld-food-delivery","Food delivery (Swiggy / Zomato)") | D26: 126
A27: logging-pipeline | B27: HLD | C27: =HYPERLINK("DESIGNS.md#hld-logging-pipeline","Logging pipeline") | D27: 131
A28: email-delivery | B28: HLD | C28: =HYPERLINK("DESIGNS.md#hld-email-delivery","Email delivery service") | D28: 133
A29: instagram | B29: HLD | C29: =HYPERLINK("DESIGNS.md#hld-instagram","Photo sharing (Instagram)") | D29: 138
A30: tiktok | B30: HLD | C30: =HYPERLINK("DESIGNS.md#hld-tiktok","Short-video feed (TikTok)") | D30: 140
A31: pinterest | B31: HLD | C31: =HYPERLINK("DESIGNS.md#hld-pinterest","Pinterest") | D31: 145
A32: reddit | B32: HLD | C32: =HYPERLINK("DESIGNS.md#hld-reddit","Community discussion and voting (Reddit)") | D32: 147
A33: netflix | B33: HLD | C33: =HYPERLINK("DESIGNS.md#hld-netflix","Video-on-demand streaming (Netflix)") | D33: 152
A34: spotify | B34: HLD | C34: =HYPERLINK("DESIGNS.md#hld-spotify","Music streaming (Spotify)") | D34: 154
A35: trending-topics | B35: HLD | C35: =HYPERLINK("DESIGNS.md#hld-trending-topics","Trending topics / top-K heavy hitters") | D35: 159
A36: cdn | B36: HLD | C36: =HYPERLINK("DESIGNS.md#hld-cdn","Content delivery network (CDN)") | D36: 161
A37: ad-serving | B37: HLD | C37: =HYPERLINK("DESIGNS.md#hld-ad-serving","Ad serving") | D37: 166
A38: recommendations | B38: HLD | C38: =HYPERLINK("DESIGNS.md#hld-recommendations","Recommendation system") | D38: 168
A39: leaderboard | B39: HLD | C39: =HYPERLINK("DESIGNS.md#hld-leaderboard","Real-time leaderboard") | D39: 173
A40: multi-region | B40: HLD | C40: =HYPERLINK("DESIGNS.md#hld-multi-region","Multi-region evolution of an earlier design") | D40: 181
A41: id-generator | B41: HLD | C41: =HYPERLINK("DESIGNS.md#hld-id-generator","Distributed unique ID generator (Snowflake)") | D41: 175
A42: package-tracking | B42: HLD | C42: =HYPERLINK("DESIGNS.md#hld-package-tracking","Package tracking (Amazon-style OA sketch)") | D42: 158
A43: logger | B43: LLD | C43: =HYPERLINK("DESIGNS.md#lld-logger","Logging framework") | D43: 41, 42
A44: parking-lot | B44: LLD | C44: =HYPERLINK("DESIGNS.md#lld-parking-lot","Parking lot") | D44: 48, 55, 153
A45: lru-cache | B45: LLD | C45: =HYPERLINK("DESIGNS.md#lld-lru-cache","LRU / LFU cache") | D45: 62
A46: rate-limiter-lld | B46: LLD | C46: =HYPERLINK("DESIGNS.md#lld-rate-limiter-lld","Rate limiter / API throttling with a controllable clock") | D46: 97, 153
A47: splitwise | B47: LLD | C47: =HYPERLINK("DESIGNS.md#lld-splitwise","Split-expense service (Splitwise)") | D47: 90
A48: elevator | B48: LLD | C48: =HYPERLINK("DESIGNS.md#lld-elevator","Elevator system") | D48: 104
A49: seat-reservation | B49: LLD | C49: =HYPERLINK("DESIGNS.md#lld-seat-reservation","Seat reservation with seat locking (BookMyShow)") | D49: 111
A50: task-scheduler | B50: LLD | C50: =HYPERLINK("DESIGNS.md#lld-task-scheduler","Task scheduler") | D50: 149
A51: vending-machine | B51: LLD | C51: =HYPERLINK("DESIGNS.md#lld-vending-machine","Vending machine (state pattern)") | D51: 142
A52: atm | B52: LLD | C52: =HYPERLINK("DESIGNS.md#lld-atm","ATM") | D52: 156
A53: tic-tac-toe | B53: LLD | C53: =HYPERLINK("DESIGNS.md#lld-tic-tac-toe","Tic-tac-toe") | D53: 180
A54: chess | B54: LLD | C54: =HYPERLINK("DESIGNS.md#lld-chess","Chess") | D54: 182
A55: snake-ladder | B55: LLD | C55: =HYPERLINK("DESIGNS.md#lld-snake-ladder","Snake and ladder") | D55: 187
A56: library | B56: LLD | C56: =HYPERLINK("DESIGNS.md#lld-library","Library management system") | D56: 157
A57: hotel-booking-lld | B57: LLD | C57: =HYPERLINK("DESIGNS.md#lld-hotel-booking-lld","Hotel booking") | D57: 189
A58: notification-lld | B58: LLD | C58: =HYPERLINK("DESIGNS.md#lld-notification-lld","Notification system") | D58: 194
A59: pub-sub | B59: LLD | C59: =HYPERLINK("DESIGNS.md#lld-pub-sub","Pub/sub message broker (in-memory)") | D59: 196
A60: file-system | B60: LLD | C60: =HYPERLINK("DESIGNS.md#lld-file-system","In-memory file system") | D60: 201
A61: food-delivery-lld | B61: LLD | C61: =HYPERLINK("DESIGNS.md#lld-food-delivery-lld","Food delivery app") | D61: 203
A62: traffic-light | B62: LLD | C62: =HYPERLINK("DESIGNS.md#lld-traffic-light","Traffic light controller") | D62: 208
A63: meeting-scheduler | B63: LLD | C63: =HYPERLINK("DESIGNS.md#lld-meeting-scheduler","Meeting room scheduler") | D63: 210
A64: chat-lld | B64: LLD | C64: =HYPERLINK("DESIGNS.md#lld-chat-lld","Chat application") | D64: 215
A65: reddit-lld | B65: LLD | C65: =HYPERLINK("DESIGNS.md#lld-reddit-lld","Community discussion platform (Reddit-like)") | D65: 217
A66: linkedin-lld | B66: LLD | C66: =HYPERLINK("DESIGNS.md#lld-linkedin-lld","LinkedIn (connections, feed)") | D66: 222
A67: calendar | B67: LLD | C67: =HYPERLINK("DESIGNS.md#lld-calendar","Calendar application") | D67: 224
A68: voting | B68: LLD | C68: =HYPERLINK("DESIGNS.md#lld-voting","Online voting system") | D68: 117
A69: url-shortener-lld | B69: LLD | C69: =HYPERLINK("DESIGNS.md#lld-url-shortener-lld","URL shortener") | D69: 119
A70: uber-lld | B70: LLD | C70: =HYPERLINK("DESIGNS.md#lld-uber-lld","Ride sharing (Uber)") | D70: 124
A71: airline | B71: LLD | C71: =HYPERLINK("DESIGNS.md#lld-airline","Airline management system") | D71: 126
A72: restaurant | B72: LLD | C72: =HYPERLINK("DESIGNS.md#lld-restaurant","Restaurant management system") | D72: 131
A73: car-rental | B73: LLD | C73: =HYPERLINK("DESIGNS.md#lld-car-rental","Car rental system") | D73: 133
A74: order-management | B74: LLD | C74: =HYPERLINK("DESIGNS.md#lld-order-management","Amazon order management") | D74: 138
A75: cricbuzz | B75: LLD | C75: =HYPERLINK("DESIGNS.md#lld-cricbuzz","Live cricket score (CricBuzz)") | D75: 140
A76: truecaller | B76: LLD | C76: =HYPERLINK("DESIGNS.md#lld-truecaller","Caller ID (Truecaller)") | D76: 145
A77: stock-exchange | B77: LLD | C77: =HYPERLINK("DESIGNS.md#lld-stock-exchange","Stock exchange order matching") | D77: 147
A78: lms | B78: LLD | C78: =HYPERLINK("DESIGNS.md#lld-lms","Learning management system") | D78: 152
A79: payment-lld | B79: LLD | C79: =HYPERLINK("DESIGNS.md#lld-payment-lld","Payment system") | D79: 154
A80: autocomplete-lld | B80: LLD | C80: =HYPERLINK("DESIGNS.md#lld-autocomplete-lld","Search autocomplete (trie service)") | D80: 159
A81: inventory | B81: LLD | C81: =HYPERLINK("DESIGNS.md#lld-inventory","Inventory management") | D81: 161
A82: feature-flags | B82: LLD | C82: =HYPERLINK("DESIGNS.md#lld-feature-flags","Feature flag system") | D82: 166
A83: snowflake-id | B83: LLD | C83: =HYPERLINK("DESIGNS.md#lld-snowflake-id","Distributed ID generator (Snowflake)") | D83: 168
A84: circuit-breaker | B84: LLD | C84: =HYPERLINK("DESIGNS.md#lld-circuit-breaker","Circuit breaker") | D84: 173
A85: retry-backoff | B85: LLD | C85: =HYPERLINK("DESIGNS.md#lld-retry-backoff","Retry with backoff") | D85: 175
A86: metrics-lld | B86: LLD | C86: =HYPERLINK("DESIGNS.md#lld-metrics-lld","Metrics and monitoring") | D86: 180
A87: auth-system | B87: LLD | C87: =HYPERLINK("DESIGNS.md#lld-auth-system","Authentication system") | D87: 182
A88: rbac | B88: LLD | C88: =HYPERLINK("DESIGNS.md#lld-rbac","Role-based access control (RBAC)") | D88: 187
A89: web-crawler-lld | B89: LLD | C89: =HYPERLINK("DESIGNS.md#lld-web-crawler-lld","Web crawler") | D89: 189
A90: recommendation-lld | B90: LLD | C90: =HYPERLINK("DESIGNS.md#lld-recommendation-lld","Recommendation engine") | D90: 194
A91: producer-consumer | B91: LLD | C91: =HYPERLINK("DESIGNS.md#lld-producer-consumer","Event-driven producer-consumer") | D91: 196

Sheet STORIES
A1: Story (real only) | B1: From | C1: Worksheet | D1: Recorded | E1: Customer Obsession | F1: Ownership | G1: Invent and Simplify | H1: Are Right, A Lot | I1: Learn and Be Curious | J1: Hire and Develop the Best | K1: Insist on the Highest Standards | L1: Think Big | M1: Bias for Action | N1: Frugality | O1: Earn Trust | P1: Dive Deep | Q1: Have Backbone; Disagree and Commit | R1: Deliver Results | S1: Strive to be Earth's Best Employer | T1: Success and Scale Bring Broad Responsibility
A2: Email pipeline: 7–10 h → about 1–1.5 h (flagship) | B2: Casepoint | C2: No | D2: No
A3: Embedding eligibility counts: 11 queries → 2 set-based | B3: Casepoint | C3: No | D3: No
A4: FOIA / regulated disclosure workflows | B4: Casepoint | C4: No | D4: No
A5: Legacy code: tracing paths before changing | B5: Casepoint | C5: No | D5: No
A6: SQL / index tuning on eDiscovery data | B6: Casepoint | C6: No | D6: No
A7: Multilingual processing | B7: Casepoint | C7: No | D7: No
A8: Production incident resolution | B8: Vision Infotech | C8: No | D8: No
A9: Client modules end to end | B9: Vision Infotech | C9: No | D9: No
A10: SignalR + FCM messaging (VCDoctor) | B10: Vision Infotech | C10: No | D10: No
A11: Payments: Stripe / PayPal / CCAvenue | B11: Vision / Zibma | C11: No | D11: No
A12: Vonage video (VCDoctor) | B12: Vision Infotech | C12: No | D12: No
A13: 100k+ record performance (ERP) | B13: Zibma Infotech | C13: No | D13: No
A14: ERP reporting / .NET Core APIs into ASP.NET | B14: Zibma Infotech | C14: No | D14: No
A15: Disagreement with a senior — FIND A REAL ONE | C15: No | D15: No
A16: Hard feedback / I was wrong — FIND A REAL ONE | C16: No | D16: No
A17: Helping a junior — only if real | C17: No | D17: No
A18: The job platform project — only after it is built | B18: Study project | C18: No | D18: No

Sheet JOURNAL
A1: Date | B1: One line: problem, decision, outcome | C1: Story candidate?

Sheet PROJECT
A1: Milestone | B1: Week | C1: Build | D1: Acceptance test | E1: Status | F1: Evidence (link / note)
A2: M1 | B2: 11 | C2: Small API, durable metadata, state machine | D2: Job readable after restart; illegal transition rejected | E2: Not started
A3: M2 | B3: 12 | C3: RabbitMQ + worker, attempt history, graceful shutdown | D3: Stopped worker → message redelivered, job finishes | E3: Not started
A4: M3 | B4: 13 | C4: Transactional outbox + relay | D4: Crash between commit and publish → job still delivered | E4: Not started
A5: M4 | B5: 14 | C5: Idempotent consumption and submission | D5: Duplicate delivery → one effect; duplicate POST → same response | E5: Not started
A6: M5 | B6: 15 | C6: Security | D6: 10 security tests pass, incl. cross-tenant 404 | E6: Not started
A7: M6 | B7: 16 | C7: Docker Compose + CI | D7: Clean clone runs; failing test blocks merge | E7: Not started
A8: M7 | B8: 17 | C8: Retries, DLQ/replay, leases/reaper, cancellation | D8: Kill worker mid-job → completes; poison → DLQ → replay | E8: Not started
A9: M8 | B9: 18 | C9: Fairness, observability, deployment | D9: Noisy tenant cannot starve; one job traced end to end | E9: Not started
A10: M9 | B10: 19 | C10: Load tests, failure tests, restore | D10: Benchmark report complete; restore verified | E10: Not started
A11: M10 | B11: 20 | C11: README, decisions, defense, scope freeze | D11: 15-minute defense recorded | E11: Not started
A12: M11 | B12: 25–28 | C12: AI increment (indexing, retrieval, evaluation, optional MCP) | D12: Measured recall@k; negative security tests | E12: Not started
A13: M12 | B13: 29 | C13: Optional: Kubernetes/KEDA or SQS port | D13: Runs, with a written limitation | E13: Not started

Sheet APPLY
A1: Company | B1: Country | C1: Route / note | D1: Tier | E1: On sponsor register? | F1: LinkedIn test | G1: Applied on | H1: Referral | I1: Stage | J1: Next action | K1: By when
A2: Thomson Reuters | B2: Canada | C2: Seeded Aug 2026 — verify route first | D2: 3A
A3: OpenText | B3: Canada | C3: Seeded Aug 2026 — verify | D3: 3A
A4: Magnet Forensics | B4: Canada | C4: Sponsorship unverified | D4: 3A
A5: Constellation Software | B5: Canada | C5: Seeded — verify | D5: 3A
A6: Xero | B6: New Zealand | C6: Seeded — verify | D6: 3B
A7: Datacom | B7: New Zealand | C7: Seeded — verify | D7: 3B
A8: Nuix | B8: Australia | C8: Stack may be Java-leaning — verify | D8: 3C
A9: Objective Corp | B9: Australia | C9: Seeded — verify | D9: 3C
A10: WiseTech | B10: Australia | C10: Seeded — verify | D10: 3C
A11: Microsoft Dublin | B11: Ireland | C11: Ireland gated on NFQ check | D11: 3E
A12: Fidelity | B12: Ireland | C12: Ireland gated on NFQ check | D12: 3E
A13: Version 1 | B13: Ireland | C13: Ireland gated on NFQ check | D13: 3E
... A18: Casepoint US (L-1 transfer) | B18: USA | C18: CLOSED — employer offers no overseas transfer | D18: struck

Sheet INTERVIEWS
A1: Company | B1: Round | C1: Date | D1: Questions asked (verbatim) | E1: What went well | F1: What went badly (exact moment) | G1: Root cause | H1: Repair action | I1: Repair by

Sheet DASHBOARD
A1: Measure | B1: Value
A2: Days done (of 224) | B2: =COUNTIF(DAILY!J2:J225,"Done")
A3: Share of days done | B3: =COUNTIF(DAILY!J2:J225,"Done")/224
A4: Problems solved independently | B4: =COUNTIF(DSA_LOG!E2:E2000,"Independent")
A5: Problems with a hint | B5: =COUNTIF(DSA_LOG!E2:E2000,"Hint")
A6: Problems failed / solution read | B6: =COUNTIF(DSA_LOG!E2:E2000,"Failed")+COUNTIF(DSA_LOG!E2:E2000,"Solution read")
A7: Concepts passing their last review | B7: =COUNTIF(REVIEW!I2:I400,"Pass")
A8: Weak items still open | B8: =COUNTA(WEAK!A2:A1000)-COUNTA(WEAK!F2:F1000)
A9: Designs done | B9: =COUNTA(DESIGNS!E2:E200)
A10: Stories recorded | B10: =COUNTIF(STORIES!D2:D60,"Yes")
A11: Journal lines | B11: =COUNTA(JOURNAL!A2:A2000)
A12: Project milestones done | B12: =COUNTIF(PROJECT!E2:E20,"Done")
A13: Applications sent | B13: =COUNTA(APPLY!G2:G500)
A14: Interviews analysed | B14: =COUNTA(INTERVIEWS!A2:A500)
